{
  "0227AbuMuhammadAzraqi.Makka": {
    "relations": [
      {
        "dest": "0227AbuMuhammadAzraqi.Makka",
        "main_rel_type": "CONT",
        "sec_rel_type": "",
        "source": "0249Azraqi.AkhbarMakka"
      }
    ]
  },
  "0227IbnMansurKhurasani.Sunan": {
    "external_id": "",
    "genre_tags": [
      "GAL@nodata",
      "_TARAJIM",
      "_HADITH",
      "_SUNAN",
      "CENT0300",
      "JK@السنن",
      "JK@كتب الحديث النبوي الشريف وتراجم الرواة",
      "Shamela@متون الحديث",
      "ShamAY@متون الحديث"
    ],
    "relations": [],
    "title_ar": [
      "سنن سعيد بن منصور (2)",
      "سنن سعيد بن منصور",
      "سنن سعيد بن منصور - ط العلمية والصميعي والألوكة",
      "سنن سعيد بن منصور ",
      "سنن سعيد بن منصور - ت الأعظمي - ت العلمية"
    ],
    "title_lat": [
      "Sunan"
    ],
    "uri": "0227IbnMansurKhurasani.Sunan",
    "versions": [
      "0227IbnMansurKhurasani.Sunan.JK001473-ara1",
      "0227IbnMansurKhurasani.Sunan.Shamela0013122-ara1",
      "0227IbnMansurKhurasani.Sunan.ShamAY0038067-ara1",
      "0227IbnMansurKhurasani.Sunan.ShamAY0033972-ara1"
    ]
  },
  "0227IbnMansurKhurasani.TafsirMinSunanSacid": {
    "external_id": "",
    "genre_tags": [
      "GAL@nodata",
      "_FIQH",
      "_TARAJIM",
      "_HADITH",
      "_SUNAN",
      "CENT0300",
      "JK@السنن",
      "JK@فقه الحديث والمذاهب الأخرى",
      "JK@كتب الحديث النبوي الشريف وتراجم الرواة",
      "Shamela@متون الحديث"
    ],
    "relations": [],
    "title_ar": [
      "سنن سعيد بن منصور (1)",
      "سنن سعيد بن منصور",
      "التفسير من سنن سعيد بن منصور - محققا",
      "التفسير من سنن سعيد بن منصور"
    ],
    "title_lat": [
      "Tafsir Min Sunan Sacid"
    ],
    "uri": "0227IbnMansurKhurasani.TafsirMinSunanSacid",
    "versions": [
      "0227IbnMansurKhurasani.TafsirMinSunanSacid.JK000784-ara1",
      "0227IbnMansurKhurasani.TafsirMinSunanSacid.Shamela0001254-ara1",
      "0227IbnMansurKhurasani.TafsirMinSunanSacid.Shamela0013008-ara1"
    ]
  },
  "0228AbuJahmBahili.Juz": {
    "external_id": "",
    "genre_tags": [
      "_HADITH",
      "_AJZA",
      "CENT0300",
      "GAL@nodata",
      "Shamela@الأجزاء الحديثية"
    ],
    "relations": [],
    "title_ar": [
      "جزء أبي الجهم العلاء بن موسى الباهلي"
    ],
    "title_lat": [
      "Juz"
    ],
    "uri": "0228AbuJahmBahili.Juz",
    "versions": [
      "0228AbuJahmBahili.Juz.Shamela0009088-ara1"
    ]
  },
  "0228IbnHammadKhuzaci.Fitan": {
    "external_id": "",
    "genre_tags": [
      "_TARIKH",
      "GAL@0750-1000CE",
      "_MILAL",
      "_HADITH",
      "_CAQAID",
      "GAL@literature-islamic",
      "GAL@period-classical",
      "_AJZA",
      "CENT0300",
      "GAL@literature-arabic",
      "GAL@hadith",
      "JK@الأجزاء الموضوعية",
      "JK@الكتب المسندة",
      "JK@كتب العقائد المسندة",
      "JK@كتب العقائد والملل",
      "ShamAY@متون الحديث",
      "Shamela@متون الحديث",
      "Shia@مصادر التاريخ"
    ],
    "relations": [],
    "title_ar": [
      "كتاب الفتن",
      "الفتن لنعيم بن حماد",
      "الفتن",
      "الفتن ",
      "الفتن لنعيم بن حماد - ط الفكر"
    ],
    "title_lat": [
      "Fitan"
    ],
    "uri": "0228IbnHammadKhuzaci.Fitan",
    "versions": [
      "0228IbnHammadKhuzaci.Fitan.JK000025-ara1",
      "0228IbnHammadKhuzaci.Fitan.ShamAY0033953-ara1",
      "0228IbnHammadKhuzaci.Fitan.Shamela0013047-ara1",
      "0228IbnHammadKhuzaci.Fitan.Shia003470-ara1"
    ]
  },
  "0228IbnMuhammadMadaini.Tacazi": {
    "external_id": "",
    "genre_tags": [
      "_HADITH",
      "_AJZA",
      "CENT0300",
      "GAL@nodata",
      "Shamela@الأجزاء الحديثية"
    ],
    "relations": [],
    "title_ar": [
      "التعازي"
    ],
    "title_lat": [
      "Tacazi"
    ],
    "uri": "0228IbnMuhammadMadaini.Tacazi",
    "versions": [
      "0228IbnMuhammadMadaini.Tacazi.Shamela0026863-ara1"
    ]
  },
  "0230AbuMushal.Nawadir": {
    "external_id": "",
    "genre_tags": [
      "_MACAJIM",
      "_GHARIB",
      "_MUSTALAHAT",
      "GAL@nodata",
      "Shamela@الغريب والمعاجم ولغة الفقه - مرقم آليا"
    ],
    "relations": [],
    "title_ar": [
      "نوادر أبي مسحل"
    ],
    "title_lat": [
      "Nawadir"
    ],
    "uri": "0230AbuMushal.Nawadir",
    "versions": [
      "0230AbuMushal.Nawadir.Shamela0005376-ara1"
    ]
  },
  "0230CaliIbnJacd.Musnad": {
    "external_id": "",
    "genre_tags": [
      "_MASANID",
      "_MACAJIM",
      "_SUNNI",
      "GAL@nodata",
      "_TARAJIM",
      "_HADITH",
      "CENT0300",
      "Shamela@متون الحديث",
      "JK@المسانيد والمعاجم",
      "JK@كتب الحديث النبوي الشريف وتراجم الرواة",
      "ShamAY@متون الحديث",
      "Shia@مصادر الحديث السنية ـ القسم العام"
    ],
    "relations": [],
    "title_ar": [
      "مسند ابن الجعد",
      "مسند ابن الجعد ",
      "مسند ابن الجعد - ط الفلاح ت عبد الهادي"
    ],
    "title_lat": [
      "Musnad"
    ],
    "uri": "0230CaliIbnJacd.Musnad",
    "versions": [
      "0230CaliIbnJacd.Musnad.Shamela0004407-ara1",
      "0230CaliIbnJacd.Musnad.JK000487-ara1",
      "0230CaliIbnJacd.Musnad.ShamAY0038024-ara1",
      "0230CaliIbnJacd.Musnad.Shia001901-ara1"
    ]
  },
  "0230IbnSacd.TabaqatKubra": {
    "external_id": "",
    "genre_tags": [
      "ShamAY@التراجم والطبقات - مرقم آليا",
      "JK@الطبقات والتراجم",
      "JK@كتب الحديث النبوي الشريف وتراجم الرواة",
      "JK@كتب الطبقات",
      "Shamela@التراجم والطبقات",
      "Shia@أهم مصادر رجال الحديث عند السنة",
      "ShamAY@التراجم والطبقات"
    ],
    "relations": [],
    "title_ar": [
      "الطبقات الكبرى",
      ""
    ],
    "title_lat": [
      "al-Ṭabaqāt al-kubrá",
      ""
    ],
    "uri": "0230IbnSacd.TabaqatKubra",
    "versions": [
      "0230IbnSacd.TabaqatKubra.ShamAY0035884-ara1",
      "0230IbnSacd.TabaqatKubra.JK000744-ara5",
      "0230IbnSacd.TabaqatKubra.Shamela0001689-ara4",
      "0230IbnSacd.TabaqatKubra.Shamela0001686-ara1",
      "0230IbnSacd.TabaqatKubra.Shamela0012416-ara3",
      "0230IbnSacd.TabaqatKubra.Shamela0007666-ara5",
      "0230IbnSacd.TabaqatKubra.Shia003044Vols-ara2",
      "0230IbnSacd.TabaqatKubra.ShamAY0034595-ara1",
      "0230IbnSacd.TabaqatKubra.Shamela0009351-ara2",
      "0230IbnSacd.TabaqatKubra.Shamela0009352-ara5",
      "0230IbnSacd.TabaqatKubra.JK000530-ara2"
    ]
  },
  "0230IbnSacd.TarjamatHasan": {
    "external_id": "",
    "genre_tags": [
      "_SHICI",
      "GAL@nodata",
      "_CAQAID",
      "_TWELVERS",
      "CENT0300",
      "Shia@من مصادر العقائد عند الشيعة الإمامية"
    ],
    "relations": [],
    "title_ar": [
      "ترجمة الإمام الحسن (ع)"
    ],
    "title_lat": [
      "Tarjamat Hasan"
    ],
    "uri": "0230IbnSacd.TarjamatHasan",
    "versions": [
      "0230IbnSacd.TarjamatHasan.Shia003988-ara1"
    ]
  },
  "0230IbnSacd.TarjamatHusayn": {
    "external_id": "",
    "genre_tags": [
      "_SHICI",
      "GAL@nodata",
      "_CAQAID",
      "_TWELVERS",
      "CENT0300",
      "Shia@من مصادر العقائد عند الشيعة الإمامية"
    ],
    "relations": [],
    "title_ar": [
      "ترجمة الإمام الحسين (ع)"
    ],
    "title_lat": [
      "Tarjamat Husayn"
    ],
    "uri": "0230IbnSacd.TarjamatHusayn",
    "versions": [
      "0230IbnSacd.TarjamatHusayn.Shia003989-ara1"
    ]
  },
  "0230YaclaIbnCibad.Juz": {
    "external_id": "",
    "genre_tags": [
      "_HADITH",
      "_AJZA",
      "CENT0300",
      "GAL@nodata",
      "Shamela@الأجزاء الحديثية"
    ],
    "relations": [],
    "title_ar": [
      "جزء يعلى بن عباد شيوخه (ضمن مجموع مطبوع باسم الفوائد لابن منده!)"
    ],
    "title_lat": [
      "Juz"
    ],
    "uri": "0230YaclaIbnCibad.Juz",
    "versions": [
      "0230YaclaIbnCibad.Juz.Shamela0009413-ara1"
    ]
  },
  "0231AbuNasrBahili.SharhDiwanDhiRumma": {
    "external_id": "",
    "genre_tags": [
      "Sham@الدواوين الشعرية"
    ],
    "relations": [],
    "title_ar": [
      "ديوان ذي الرمة شرح الباهلي",
      "ديوان ذي الرمة شرح أبي نصر الباهلي رواية ثعلب"
    ],
    "title_lat": [
      "Sharh Diwan Dhi Rumma"
    ],
    "uri": "0231AbuNasrBahili.SharhDiwanDhiRumma",
    "versions": [
      "0231AbuNasrBahili.SharhDiwanDhiRumma.Sham19Y0016545-ara1"
    ]
  },
  "0231AbuTamam.Diwan": {
    "external_id": "",
    "genre_tags": [
      "ShamAY@الدواوين الشعرية - مرقم آليا",
      "JK@دواوين الشعر العربي",
      "JK@عباسي"
    ],
    "relations": [],
    "title_ar": [
      "ديوان أبي تمام ",
      "ديوان أبي تمام",
      "ديوان أبو تمام"
    ],
    "title_lat": [
      "Diwan"
    ],
    "uri": "0231AbuTamam.Diwan",
    "versions": [
      "0231AbuTamam.Diwan.ShamAY0037821-ara1",
      "0231AbuTamam.Diwan.JK007583-ara1"
    ]
  },
  "0231AbuTamam.Wahshiyyat": {
    "external_id": "",
    "genre_tags": [
      "_ADAB",
      "GAL@poetry",
      "CENT0300",
      "GAL@0750-1000CE",
      "GAL@literature-islamic",
      "GAL@period-classical",
      "_BALAGHA",
      "GAL@literature-arabic",
      "Shamela@الأدب والبلاغة"
    ],
    "relations": [],
    "title_ar": [
      "الوحشيات وهو الحماسة الصغرى"
    ],
    "title_lat": [
      "Wahshiyyat"
    ],
    "uri": "0231AbuTamam.Wahshiyyat",
    "versions": [
      "0231AbuTamam.Wahshiyyat.Shamela0036082-ara1"
    ]
  },
  "0231IbnMirdasSarraj.Hadith": {
    "external_id": "",
    "genre_tags": [
      "_HADITH",
      "CENT0300",
      "_MAKHTUTAT",
      "GAL@nodata",
      "Shamela@مخطوطات حديثية"
    ],
    "relations": [],
    "title_ar": [
      "حديث خالد بن مرداس السراج"
    ],
    "title_lat": [
      "Hadith"
    ],
    "uri": "0231IbnMirdasSarraj.Hadith",
    "versions": [
      "0231IbnMirdasSarraj.Hadith.Shamela0029705-ara1"
    ]
  },
  "0231IbnSacdanDarir.WaqfWaIbtida": {
    "external_id": "",
    "genre_tags": [
      "Sham@التجويد والقراءات"
    ],
    "relations": [],
    "title_ar": [
      "الوقف والابتداء في كتاب الله عز وجل"
    ],
    "title_lat": [
      "Waqf Wa Ibtida"
    ],
    "uri": "0231IbnSacdanDarir.WaqfWaIbtida",
    "versions": [
      "0231IbnSacdanDarir.WaqfWaIbtida.Sham19Y0017843-ara1"
    ]
  },
  "0231IbnSallamJumahi.TabaqatFuhulShucara": {
    "external_id": "",
    "genre_tags": [
      "_ADAB",
      "_TABAQAT",
      "GAL@nodata",
      "_TARAJIM",
      "_TARIKH",
      "PPE",
      "CENT0300",
      "JK@الطبقات والتراجم",
      "JK@تراجم الأدباء",
      "JK@كتب التراجم التاريخية",
      "Shamela@التراجم والطبقات"
    ],
    "relations": [],
    "title_ar": [
      "طبقات فحول الشعراء",
      ""
    ],
    "title_lat": [
      "ṭabaqāt fuḥūl al-šuʿarāʾ",
      ""
    ],
    "uri": "0231IbnSallamJumahi.TabaqatFuhulShucara",
    "versions": [
      "0231IbnSallamJumahi.TabaqatFuhulShucara.JK001296-ara1",
      "0231IbnSallamJumahi.TabaqatFuhulShucara.Shamela0006738-ara1"
    ]
  },
  "0231IbnZiyadAcrabi.AsmaKhayl": {
    "external_id": "",
    "genre_tags": [
      "_ADAB",
      "_MACAJIM",
      "_GHARIB",
      "_MUSTALAHAT",
      "CENT0300",
      "GAL@0750-1000CE",
      "GAL@philology",
      "GAL@literature-islamic",
      "GAL@period-classical",
      "_BALAGHA",
      "GAL@literature-arabic",
      "Shamela@الأدب والبلاغة",
      "JK@المعاجم",
      "JK@كتب المعاجم والغريب والمصطلحات"
    ],
    "relations": [],
    "title_ar": [
      "أسماء خيل العرب وفرسانها"
    ],
    "title_lat": [
      "Asma Khayl"
    ],
    "uri": "0231IbnZiyadAcrabi.AsmaKhayl",
    "versions": [
      "0231IbnZiyadAcrabi.AsmaKhayl.Shamela0000770-ara1",
      "0231IbnZiyadAcrabi.AsmaKhayl.JK010643-ara1"
    ]
  },
  "0232CabdAllahIbnCawnKharraz.Nuskha": {
    "external_id": "",
    "genre_tags": [
      "ShamAY@الأجزاء الحديثية"
    ],
    "relations": [],
    "title_ar": [
      "نسخة عبد الله بن عون الخراز",
      "نسخة عبد الله بن عون الخراز عن شيوخه ",
      "نسخة عبد الله بن عون الخراز عن شيوخه"
    ],
    "title_lat": [
      "Nuskha"
    ],
    "uri": "0232CabdAllahIbnCawnKharraz.Nuskha",
    "versions": [
      "0232CabdAllahIbnCawnKharraz.Nuskha.ShamAY0033610-ara1"
    ]
  },
  "0232CisaIbnSacidShashi.Hadith": {
    "external_id": "",
    "genre_tags": [
      "ShamAY@الأجزاء الحديثية"
    ],
    "relations": [],
    "title_ar": [
      "من حديث أبي سعيد عيسى بن سالم الشاشي",
      "من حديث أبي سعيد عيسى بن سالم الشاشي "
    ],
    "title_lat": [
      "Hadith"
    ],
    "uri": "0232CisaIbnSacidShashi.Hadith",
    "versions": [
      "0232CisaIbnSacidShashi.Hadith.ShamAY0033604-ara1"
    ]
  },
  "0233IbnCaidhDimashqi.Sawaif": {
    "external_id": "",
    "genre_tags": [
      "ShamAY@التاريخ - مرقم آليا"
    ],
    "relations": [],
    "title_ar": [
      "كتاب الصوائف",
      "الصوائف"
    ],
    "title_lat": [
      "Sawaif"
    ],
    "uri": "0233IbnCaidhDimashqi.Sawaif",
    "versions": [
      "0233IbnCaidhDimashqi.Sawaif.ShamAY0037161-ara1"
    ]
  },
  "0233YahyaIbnMacin.HadithYahya": {
    "external_id": "",
    "genre_tags": [
      "GAL@nodata",
      "_TARAJIM",
      "_MISC",
      "_HADITH",
      "_AJZA",
      "_FAWAID",
      "CENT0300",
      "JK@أجزاء حديثية",
      "JK@كتب الحديث النبوي الشريف وتراجم الرواة",
      "JK@من كتب الفوائد",
      "Shamela@الأجزاء الحديثية"
    ],
    "relations": [],
    "title_ar": [
      "الجزء الثاني من حديث يحيى بن معين ( الفوائد )",
      "الجزء الثاني من حديث يحيى بن معين الفوائد",
      "جزء فيه أحاديث يحيى بن معين"
    ],
    "title_lat": [
      "Hadith Yahya"
    ],
    "uri": "0233YahyaIbnMacin.HadithYahya",
    "versions": [
      "0233YahyaIbnMacin.HadithYahya.JK001484-ara1",
      "0233YahyaIbnMacin.HadithYahya.Shamela0009294-ara1",
      "0233YahyaIbnMacin.HadithYahya.Shamela0011037-ara1"
    ]
  },
  "0233YahyaIbnMacin.MacrifatRijal": {
    "external_id": "",
    "genre_tags": [
      "_TABAQAT",
      "GAL@nodata",
      "_TARAJIM",
      "PPE",
      "CENT0300",
      "Shamela@التراجم والطبقات"
    ],
    "relations": [],
    "title_ar": [
      "معرفة الرجال عن يحيى بن معين وفيه عن علي بن المديني وأبي بكر بن أبي شيبة ومحمد بن عبد الله بن نمير وغيرهم/ رواية أحمد بن محمد بن القاسم بن محرز"
    ],
    "title_lat": [
      "Macrifat Rijal"
    ],
    "uri": "0233YahyaIbnMacin.MacrifatRijal",
    "versions": [
      "0233YahyaIbnMacin.MacrifatRijal.Shamela0000101-ara1"
    ]
  },
  "0233YahyaIbnMacin.MinKalamFiRijal": {
    "external_id": "",
    "genre_tags": [
      "_CILAL",
      "GAL@nodata",
      "_TARAJIM",
      "_HADITH",
      "_SUALAT",
      "PPE",
      "CENT0300",
      "JK@السؤالات",
      "JK@كتب الحديث النبوي الشريف وتراجم الرواة",
      "Shamela@العلل والسؤالات"
    ],
    "relations": [],
    "title_ar": [
      "من كلام أبي زكريا في الرجال",
      "!من كلام أبي زكريا يحيى بن معين في الرجال",
      "من كلام أبي زكريا يحيى بن معين في الرجال (رواية طهمان)"
    ],
    "title_lat": [
      "Min Kalam Fi Rijal"
    ],
    "uri": "0233YahyaIbnMacin.MinKalamFiRijal",
    "versions": [
      "0233YahyaIbnMacin.MinKalamFiRijal.JK000716-ara1",
      "0233YahyaIbnMacin.MinKalamFiRijal.Shamela0005954-ara1"
    ]
  },
  "0233YahyaIbnMacin.SualatIbnJunayd": {
    "external_id": "",
    "genre_tags": [
      "_CILAL",
      "GAL@nodata",
      "CENT0300",
      "_SUALAT",
      "Shamela@العلل والسؤالات",
      "ShamAY@العلل والسؤالات"
    ],
    "relations": [],
    "title_ar": [
      "سؤالات ابن الجنيد لأبي زكريا يحيى بن معين",
      "سؤالات ابن الجنيد للإمام يحيى بن معين - ط الفاروق",
      "سؤالات أبي إسحاق إبراهيم بن الجنيد للإمام يحيى بن معين ",
      "سؤالات أبي إسحاق إبراهيم بن الجنيد للإمام يحيى بن معين"
    ],
    "title_lat": [
      "Sualat Ibn Junayd"
    ],
    "uri": "0233YahyaIbnMacin.SualatIbnJunayd",
    "versions": [
      "0233YahyaIbnMacin.SualatIbnJunayd.Shamela0012698-ara1",
      "0233YahyaIbnMacin.SualatIbnJunayd.ShamAY0034156-ara1"
    ]
  },
  "0234AbuKhaythamaNisai.Cilm": {
    "external_id": "",
    "genre_tags": [
      "_AKHLAQ",
      "_SUNNI",
      "GAL@nodata",
      "_FIQH",
      "_MASAIL",
      "_HADITH",
      "_USUL",
      "_AJZA",
      "CENT0300",
      "JK@الأجزاء الموضوعية",
      "JK@كتب الأخلاق والسلوك",
      "JK@مسائل فقهية وأصولية",
      "JK@مواضيع مسندة في الأخلاق والتزكية",
      "Shamela@الأجزاء الحديثية",
      "Shia@مصادر الحديث السنية ـ القسم العام"
    ],
    "relations": [],
    "title_ar": [
      "العلم",
      "كتاب العلم"
    ],
    "title_lat": [
      "Cilm"
    ],
    "uri": "0234AbuKhaythamaNisai.Cilm",
    "versions": [
      "0234AbuKhaythamaNisai.Cilm.JK000493-ara1",
      "0234AbuKhaythamaNisai.Cilm.Shamela0007777-ara1",
      "0234AbuKhaythamaNisai.Cilm.Shia001903-ara1"
    ]
  },
  "0234CaliIbnMadini.Cilal": {
    "external_id": "",
    "genre_tags": [
      "_MAWDUC",
      "GAL@nodata",
      "_DACIF",
      "_HADITH",
      "_SUALAT",
      "_AHKAM",
      "_CILAL",
      "CENT0300",
      "Shamela@العلل والسؤالات",
      "JK@العلل",
      "JK@كتب الأحاديث الضعيفة والموضوعة",
      "JK@كتب العلل والأحكام",
      "ShamAY@العلل والسؤالات"
    ],
    "relations": [],
    "title_ar": [
      "العلل",
      "العلل للمديني",
      "العلل ومعرفة الرجال",
      "العلل ومعرفة الرجال لابن المديني - ط الفاروق",
      "العلل ومعرفة الرجال "
    ],
    "title_lat": [
      "Cilal"
    ],
    "uri": "0234CaliIbnMadini.Cilal",
    "versions": [
      "0234CaliIbnMadini.Cilal.Shamela0006038-ara1",
      "0234CaliIbnMadini.Cilal.JK000708-ara1",
      "0234CaliIbnMadini.Cilal.ShamAY0034150-ara1"
    ]
  },
  "0234CaliIbnMadini.SualatIbnAbiShayba": {
    "external_id": "",
    "genre_tags": [
      "GAL@nodata",
      "_TARAJIM",
      "_HADITH",
      "_SUALAT",
      "_CILAL",
      "CENT0300",
      "JK@السؤالات",
      "JK@كتب الحديث النبوي الشريف وتراجم الرواة",
      "Shia@مصادر الحديث السنية ـ القسم العام",
      "Shamela@العلل والسؤالات"
    ],
    "relations": [],
    "title_ar": [
      "سؤالات ابن أبي شيبة",
      "سؤالات محمد بن عثمان بن أبي شيبة لعلي بن المديني"
    ],
    "title_lat": [
      "Sualat Ibn Abi Shayba"
    ],
    "uri": "0234CaliIbnMadini.SualatIbnAbiShayba",
    "versions": [
      "0234CaliIbnMadini.SualatIbnAbiShayba.JK000655-ara1",
      "0234CaliIbnMadini.SualatIbnAbiShayba.Shia001902-ara1",
      "0234CaliIbnMadini.SualatIbnAbiShayba.Shamela0005947-ara1"
    ]
  },
  "0234CaliIbnMadini.TasmiyatManRuwiya": {
    "external_id": "",
    "genre_tags": [
      "_TABAQAT",
      "GAL@nodata",
      "_TARAJIM",
      "_MISC",
      "_HADITH",
      "PPE",
      "CENT0300",
      "JK@أخرى",
      "JK@كتب الحديث النبوي الشريف وتراجم الرواة",
      "JK@كتب الطبقات",
      "Shamela@التراجم والطبقات"
    ],
    "relations": [],
    "title_ar": [
      "تسمية من روي عنه من أولاد العشرة"
    ],
    "title_lat": [
      "Tasmiyat Man Ruwiya"
    ],
    "uri": "0234CaliIbnMadini.TasmiyatManRuwiya",
    "versions": [
      "0234CaliIbnMadini.TasmiyatManRuwiya.JK000504-ara1",
      "0234CaliIbnMadini.TasmiyatManRuwiya.Shamela0005893-ara1"
    ]
  },
  "0235DikJinn.Diwan": {
    "external_id": "",
    "genre_tags": [
      "_SHICR",
      "GAL@poetry",
      "GAL@0750-1000CE",
      "_SHICR_CABBASI",
      "GAL@literature-islamic",
      "GAL@period-classical",
      "GAL@literature-arabic",
      "JK@دواوين الشعر العربي",
      "JK@عباسي",
      "ShamAY@الدواوين الشعرية - مرقم آليا"
    ],
    "relations": [],
    "title_ar": [
      "ديوان ديك الجن",
      "ديوان ديك الجن "
    ],
    "title_lat": [
      "Diwan"
    ],
    "uri": "0235DikJinn.Diwan",
    "versions": [
      "0235DikJinn.Diwan.JK007616-ara1",
      "0235DikJinn.Diwan.ShamAY0037948-ara1"
    ]
  },
  "0235HanunIbnYuhannaIbnSalt.TibbNujumi": {
    "external_id": "",
    "genre_tags": [],
    "relations": [],
    "title_ar": [
      "الطب النجومي"
    ],
    "title_lat": [
      "al-Ṭibb al-nuǧūmī"
    ],
    "uri": "0235HanunIbnYuhannaIbnSalt.TibbNujumi",
    "versions": [
      "0235HanunIbnYuhannaIbnSalt.TibbNujumi.AOCP20251104001-ara1"
    ]
  },
  "0235IbnAbiShayba.Adab": {
    "external_id": "",
    "genre_tags": [
      "GAL@nodata",
      "_TARAJIM",
      "_HADITH",
      "_AJZA",
      "CENT0300",
      "JK@أجزاء حديثية",
      "JK@كتب الحديث النبوي الشريف وتراجم الرواة",
      "Shamela@متون الحديث"
    ],
    "relations": [],
    "title_ar": [
      "كتاب الأدب",
      "الأدب لابن أبي شيبة"
    ],
    "title_lat": [
      "Adab"
    ],
    "uri": "0235IbnAbiShayba.Adab",
    "versions": [
      "0235IbnAbiShayba.Adab.JK009175-ara1",
      "0235IbnAbiShayba.Adab.Shamela0000638-ara1"
    ]
  },
  "0235IbnAbiShayba.Iman": {
    "external_id": "",
    "genre_tags": [
      "_HADITH",
      "_AJZA",
      "CENT0300",
      "GAL@nodata",
      "Shamela@الأجزاء الحديثية"
    ],
    "relations": [],
    "title_ar": [
      "كتاب الإيمان"
    ],
    "title_lat": [
      "Iman"
    ],
    "uri": "0235IbnAbiShayba.Iman",
    "versions": [
      "0235IbnAbiShayba.Iman.Shamela0007767-ara1"
    ]
  },
  "0235IbnAbiShayba.KhalqAdamWaWiladatNabi": {
    "external_id": "",
    "genre_tags": [
      "ShamAY@مخطوطات حديثية"
    ],
    "relations": [],
    "title_ar": [
      "ذكر خلق آدم وخطيئته وتوبته وأبواب في ولادة النبي صلى الله عليه وسلم - مخطوط ",
      "ذكر خلق آدم وخطيئته وتوبته وأبواب في ولادة النبي صلى الله عليه وسلم - مخطوط",
      "ذكر خلق آدم لمحمد بن عثمان بن أبي شيبة - مخطوط"
    ],
    "title_lat": [
      "Khalq Adam Wa Wiladat Nabi"
    ],
    "uri": "0235IbnAbiShayba.KhalqAdamWaWiladatNabi",
    "versions": [
      "0235IbnAbiShayba.KhalqAdamWaWiladatNabi.ShamAY0032908-ara1"
    ]
  },
  "0235IbnAbiShayba.Musannaf": {
    "external_id": "",
    "genre_tags": [
      "ShamAY@متون الحديث",
      "Shia@مصادر الحديث السنية ـ القسم العام",
      "JK@المصنفات والآثار",
      "JK@فقه الحديث والمذاهب الأخرى",
      "JK@كتب الحديث النبوي الشريف وتراجم الرواة",
      "JK@كتب المصنفات والآثار",
      "Shamela@متون الحديث"
    ],
    "relations": [],
    "title_ar": [
      "مصنف ابن أبي شيبة (الفكر)",
      "المصنف",
      "المصنف ",
      "الكتاب المصنف في الأحاديث والآثار",
      "مصنف ابن أبي شيبة",
      "مصنف ابن أبي شيبة (عوامة)",
      "مصنف ابن أبي شيبة "
    ],
    "title_lat": [
      "Musannaf"
    ],
    "uri": "0235IbnAbiShayba.Musannaf",
    "versions": [
      "0235IbnAbiShayba.Musannaf.ShamAY0033966-ara1",
      "0235IbnAbiShayba.Musannaf.Shia001904Vols-ara1",
      "0235IbnAbiShayba.Musannaf.JK000786-ara1",
      "0235IbnAbiShayba.Musannaf.ShamAY0033967-ara1",
      "0235IbnAbiShayba.Musannaf.ShamAY0033931-ara1",
      "0235IbnAbiShayba.Musannaf.Shamela0009944-ara1"
    ]
  },
  "0235IbnAbiShayba.Musnad": {
    "external_id": "",
    "genre_tags": [
      "_MASANID",
      "_MACAJIM",
      "GAL@history-world",
      "_TARAJIM",
      "GAL@history",
      "GAL@0750-1000CE",
      "_HADITH",
      "GAL@literature-arabic",
      "GAL@literature-islamic",
      "GAL@period-classical",
      "CENT0300",
      "GAL@historiography",
      "GAL@history-imperial",
      "Shamela@متون الحديث",
      "JK@المسانيد والمعاجم",
      "JK@كتب الحديث النبوي الشريف وتراجم الرواة"
    ],
    "relations": [],
    "title_ar": [
      "مسند ابن أبي شيبة"
    ],
    "title_lat": [
      "Musnad"
    ],
    "uri": "0235IbnAbiShayba.Musnad",
    "versions": [
      "0235IbnAbiShayba.Musnad.Shamela0013155-ara1",
      "0235IbnAbiShayba.Musnad.JK007049-ara1"
    ]
  },
  "0235IbnYunusBaghdadi.Qada": {
    "external_id": "",
    "genre_tags": [
      "GAL@nodata",
      "_FIQH",
      "_MASAIL",
      "_HADITH",
      "_AJZA",
      "CENT0300",
      "JK@كتب الفقه الإسلامي",
      "JK@مسائل فقهية",
      "Shamela@الأجزاء الحديثية"
    ],
    "relations": [],
    "title_ar": [
      "القضاء",
      "كتاب القضاء لسريج بن يونس"
    ],
    "title_lat": [
      "Qada"
    ],
    "uri": "0235IbnYunusBaghdadi.Qada",
    "versions": [
      "0235IbnYunusBaghdadi.Qada.JK011413-ara1",
      "0235IbnYunusBaghdadi.Qada.Shamela0008219-ara1"
    ]
  },
  "0236AbuCabdAllahZubayri.NasabQuraysh": {
    "external_id": "",
    "genre_tags": [
      "GAL@history-world",
      "_TARAJIM",
      "_TARIKH",
      "GAL@history",
      "GAL@0750-1000CE",
      "_ANSAB",
      "GAL@literature-arabic",
      "GAL@literature-islamic",
      "GAL@period-classical",
      "CENT0300",
      "GAL@historiography",
      "GAL@history-imperial",
      "Shamela@الأنساب",
      "JK@كتب التراجم التاريخية"
    ],
    "relations": [],
    "title_ar": [
      "نسب قريش"
    ],
    "title_lat": [
      "Nasab Quraysh"
    ],
    "uri": "0236AbuCabdAllahZubayri.NasabQuraysh",
    "versions": [
      "0236AbuCabdAllahZubayri.NasabQuraysh.Shamela0002922-ara1",
      "0236AbuCabdAllahZubayri.NasabQuraysh.JK009223-ara1"
    ]
  },
  "0238IbnHabibQurtubi.AdabNisa": {
    "external_id": "",
    "genre_tags": [
      "_HADITH",
      "_AJZA",
      "CENT0300",
      "GAL@nodata",
      "Shamela@الأجزاء الحديثية"
    ],
    "relations": [],
    "title_ar": [
      "كتاب أدب النساء",
      "كتاب الغاية و النهاية"
    ],
    "title_lat": [
      "Kitāb adab al-nisāʾ",
      "Kitāb al-ġāyaŧ wa al-nihāyaŧ"
    ],
    "uri": "0238IbnHabibQurtubi.AdabNisa",
    "versions": [
      "0238IbnHabibQurtubi.AdabNisa.Shamela0026808-ara1"
    ]
  },
  "0238IbnHabibQurtubi.AshratSaca": {
    "external_id": "",
    "genre_tags": [
      "_HADITH",
      "_AJZA",
      "CENT0300",
      "GAL@nodata",
      "Shamela@الأجزاء الحديثية"
    ],
    "relations": [],
    "title_ar": [
      "أشراط الساعة وذهاب الأخيار وبقاء الأشرار"
    ],
    "title_lat": [
      "Ashrat Saca"
    ],
    "uri": "0238IbnHabibQurtubi.AshratSaca",
    "versions": [
      "0238IbnHabibQurtubi.AshratSaca.Shamela0026569-ara1"
    ]
  },
  "0238IbnHabibQurtubi.MukhtasarFiTibb": {
    "external_id": "",
    "genre_tags": [
      "_CULUM",
      "_TIBB",
      "GAL@nodata",
      "_MISC",
      "CENT0300",
      "JK@كتب العلوم والطب",
      "Shamela@علوم أخرى"
    ],
    "relations": [],
    "title_ar": [
      "العلاج بالأعشاب",
      "(مختصر في الطب) العلاج بالأغذية والأعشاب في بلاد المغرب"
    ],
    "title_lat": [
      "Mukhtasar Fi Tibb"
    ],
    "uri": "0238IbnHabibQurtubi.MukhtasarFiTibb",
    "versions": [
      "0238IbnHabibQurtubi.MukhtasarFiTibb.JK007013-ara1",
      "0238IbnHabibQurtubi.MukhtasarFiTibb.Shamela0010705-ara1"
    ]
  },
  "0238IbnHabibQurtubi.Riba": {
    "external_id": "",
    "genre_tags": [
      "ShamAY@الأجزاء الحديثية"
    ],
    "relations": [],
    "title_ar": [
      "الربا لابن حبيب",
      "كتاب الربا",
      "كتاب الربا "
    ],
    "title_lat": [
      "Riba"
    ],
    "uri": "0238IbnHabibQurtubi.Riba",
    "versions": [
      "0238IbnHabibQurtubi.Riba.ShamAY0033706-ara1"
    ]
  },
  "0238IbnHabibQurtubi.WadihaFiSunan": {
    "external_id": "",
    "genre_tags": [
      "ShamAY@متون الحديث - مرقم آليا"
    ],
    "relations": [],
    "title_ar": [
      "كتاب الواضحة في السنن",
      "كتاب الواضحة في السنن "
    ],
    "title_lat": [
      "Wadiha Fi Sunan"
    ],
    "uri": "0238IbnHabibQurtubi.WadihaFiSunan",
    "versions": [
      "0238IbnHabibQurtubi.WadihaFiSunan.ShamAY0035251-ara1"
    ]
  },
  "0238IbnHabibQurtubi.WasfFirdaws": {
    "external_id": "",
    "genre_tags": [
      "ShamAY@الأجزاء الحديثية"
    ],
    "relations": [],
    "title_ar": [
      "وصف الفردوس",
      "وصف الفردوس لعبد الملك بن حبيب",
      "وصف الفردوس لعبد الملك بن حبيب "
    ],
    "title_lat": [
      "Wasf Firdaws"
    ],
    "uri": "0238IbnHabibQurtubi.WasfFirdaws",
    "versions": [
      "0238IbnHabibQurtubi.WasfFirdaws.ShamAY0033596-ara1"
    ]
  },
  "0238IbnRahawayh.Musnad": {
    "external_id": "",
    "genre_tags": [
      "_MASANID",
      "_MACAJIM",
      "_SUNNI",
      "_TARAJIM",
      "GAL@0750-1000CE",
      "_HADITH",
      "GAL@literature-islamic",
      "GAL@period-classical",
      "CENT0300",
      "GAL@literature-arabic",
      "GAL@hadith",
      "JK@المسانيد والمعاجم",
      "JK@كتب الحديث النبوي الشريف وتراجم الرواة",
      "Shamela@متون الحديث - مرقم آليا",
      "Shamela@متون الحديث",
      "Shia@مصادر الحديث السنية ـ القسم العام"
    ],
    "relations": [],
    "title_ar": [
      "مسند إسحاق بن راهويه",
      "مسند إسحاق بن راهويه - مسند ابن عباس",
      "مسند ابن راهويه"
    ],
    "title_lat": [
      "Musnad"
    ],
    "uri": "0238IbnRahawayh.Musnad",
    "versions": [
      "0238IbnRahawayh.Musnad.JK000479-ara1",
      "0238IbnRahawayh.Musnad.Shamela0001423-ara1",
      "0238IbnRahawayh.Musnad.Shamela0013159-ara1",
      "0238IbnRahawayh.Musnad.Shia001913Vols-ara1"
    ]
  },
  "0238MuhammadBurjulani.KaramWaJawd": {
    "external_id": "",
    "genre_tags": [
      "_HADITH",
      "_AJZA",
      "CENT0300",
      "GAL@nodata",
      "Shamela@الأجزاء الحديثية",
      "Shia@مصادر الحديث السنية ـ القسم العام",
      "JK@الأجزاء الموضوعية",
      "JK@الكتب المسندة",
      "JK@كتب الأخلاق والسلوك",
      "JK@مواضيع مسندة في الأخلاق والتزكية"
    ],
    "relations": [],
    "title_ar": [
      "من حديث أبي عبد الله الحسين بن محمد ابن العسكري عن شيوخه (مطبوع مع كتاب الكرم والجود للمؤلف)",
      "الكرم والجود وسخاء النفوس",
      "الكرم والجود"
    ],
    "title_lat": [
      "Karam Wa Jawd"
    ],
    "uri": "0238MuhammadBurjulani.KaramWaJawd",
    "versions": [
      "0238MuhammadBurjulani.KaramWaJawd.Shamela0007819-ara1",
      "0238MuhammadBurjulani.KaramWaJawd.Shamela0007755-ara1",
      "0238MuhammadBurjulani.KaramWaJawd.Shia001912-ara1",
      "0238MuhammadBurjulani.KaramWaJawd.JK000047-ara1"
    ]
  },
  "0239CumaraIbnCaqil.Diwan": {
    "external_id": "",
    "genre_tags": [
      "Sham@الدواوين الشعرية"
    ],
    "relations": [],
    "title_ar": [
      "ديوان عمارة بن عقيل (المتوفي: 239 ه)",
      "ديوان عمارة بن عقيل"
    ],
    "title_lat": [
      "Diwan"
    ],
    "uri": "0239CumaraIbnCaqil.Diwan",
    "versions": [
      "0239CumaraIbnCaqil.Diwan.Sham19Y0149872-ara1"
    ]
  },
  "0239IbnGhawri.Majlis": {
    "external_id": "",
    "genre_tags": [
      "ShamAY@الأجزاء الحديثية"
    ],
    "relations": [],
    "title_ar": [
      "جزء فيه مجلس من إملاء أبي الفرج محمد بن أحمد المعروف بابن الغوري",
      "مجلس ابن الغوري",
      "جزء فيه مجلس من إملاء أبي الفرج محمد بن أحمد المعروف بابن الغوري "
    ],
    "title_lat": [
      "Majlis"
    ],
    "uri": "0239IbnGhawri.Majlis",
    "versions": [
      "0239IbnGhawri.Majlis.ShamAY0033638-ara1"
    ]
  },
  "0240AbuHafsIbnZuraraTarsusi.Nuskha": {
    "external_id": "",
    "genre_tags": [
      "ShamAY@مخطوطات حديثية"
    ],
    "relations": [],
    "title_ar": [
      "نسخة أبي حفص عمر بن زرارة الحدثي - مخطوط ",
      "نسخة أبي حفص عمر بن زرارة الحدثي - مخطوط"
    ],
    "title_lat": [
      "Nuskha"
    ],
    "uri": "0240AbuHafsIbnZuraraTarsusi.Nuskha",
    "versions": [
      "0240AbuHafsIbnZuraraTarsusi.Nuskha.ShamAY0032875-ara1"
    ]
  },
  "0240CabdSamadIbnMucadhdhal.Diwan": {
    "external_id": "",
    "genre_tags": [
      "ShamAY@الدواوين الشعرية - مرقم آليا",
      "JK@دواوين الشعر العربي",
      "JK@عباسي"
    ],
    "relations": [],
    "title_ar": [
      "ديوان عبد الصمد بن المعذل ",
      "ديوان عبد الصمد بن المعذل"
    ],
    "title_lat": [
      "Diwan"
    ],
    "uri": "0240CabdSamadIbnMucadhdhal.Diwan",
    "versions": [
      "0240CabdSamadIbnMucadhdhal.Diwan.ShamAY0037953-ara1",
      "0240CabdSamadIbnMucadhdhal.Diwan.JK007619-ara1"
    ]
  },
  "0240IbnKhayyatCusfuri.Musnad": {
    "external_id": "",
    "genre_tags": [
      "_HADITH",
      "_AJZA",
      "CENT0300",
      "GAL@nodata",
      "Shamela@الأجزاء الحديثية"
    ],
    "relations": [],
    "title_ar": [
      "مسند خليفة بن خياط"
    ],
    "title_lat": [
      "Musnad"
    ],
    "uri": "0240IbnKhayyatCusfuri.Musnad",
    "versions": [
      "0240IbnKhayyatCusfuri.Musnad.Shamela0012863-ara1"
    ]
  },
  "0240IbnKhayyatCusfuri.Tabaqat": {
    "external_id": "",
    "genre_tags": [
      "_TABAQAT",
      "_SUNNI",
      "GAL@nodata",
      "_TARAJIM",
      "_HADITH",
      "PPE",
      "CENT0300",
      "JK@الطبقات والتراجم",
      "JK@كتب الحديث النبوي الشريف وتراجم الرواة",
      "JK@كتب الطبقات",
      "Shia@أهم مصادر رجال الحديث عند السنة",
      "Shamela@التراجم والطبقات",
      "ShamAY@التراجم والطبقات"
    ],
    "relations": [],
    "title_ar": [
      "الطبقات لابن خياط",
      "الطبقات",
      "طبقات خليفة",
      "طبقات خليفة بن خياط",
      "الطبقات لخليفة بن خياط - طيبة"
    ],
    "title_lat": [
      "Tabaqat"
    ],
    "uri": "0240IbnKhayyatCusfuri.Tabaqat",
    "versions": [
      "0240IbnKhayyatCusfuri.Tabaqat.JK000516-ara2",
      "0240IbnKhayyatCusfuri.Tabaqat.Shia003056-ara1",
      "0240IbnKhayyatCusfuri.Tabaqat.Shamela0008682-ara1",
      "0240IbnKhayyatCusfuri.Tabaqat.ShamAY0034615-ara1"
    ]
  },
  "0240IbnKhayyatCusfuri.Tarikh": {
    "external_id": "",
    "genre_tags": [
      "_SUNNI",
      "GAL@nodata",
      "_TARAJIM",
      "_TARIKH",
      "_HADITH",
      "PPE",
      "CENT0300",
      "Shamela@التاريخ",
      "JK@التاريخ العام",
      "JK@التواريخ العامة",
      "JK@كتب التاريخ",
      "Shia@أهم مصادر رجال الحديث عند السنة"
    ],
    "relations": [],
    "title_ar": [
      "تاريخ خليفة بن خياط"
    ],
    "title_lat": [
      "Tarikh"
    ],
    "uri": "0240IbnKhayyatCusfuri.Tarikh",
    "versions": [
      "0240IbnKhayyatCusfuri.Tarikh.Shamela0006615-ara1",
      "0240IbnKhayyatCusfuri.Tarikh.JK000412-ara1",
      "0240IbnKhayyatCusfuri.Tarikh.Shia003055-ara2"
    ]
  },
  "0240IbnYahyaKinani.Hida": {
    "external_id": "",
    "genre_tags": [
      "GAL@0750-1000CE",
      "_MILAL",
      "_CAQAID",
      "GAL@literature-islamic",
      "GAL@period-classical",
      "GAL@dogmatics",
      "CENT0300",
      "GAL@literature-arabic",
      "JK@كتب العقائد والملل",
      "JK@مواضيع عقدية",
      "Shamela@العقيدة"
    ],
    "relations": [],
    "title_ar": [
      "الحيدة والاعتذار",
      "الحيدة والاعتذار في الرد على من قال بخلق القرآن"
    ],
    "title_lat": [
      "Hida"
    ],
    "uri": "0240IbnYahyaKinani.Hida",
    "versions": [
      "0240IbnYahyaKinani.Hida.JK012049-ara1",
      "0240IbnYahyaKinani.Hida.Shamela0007610-ara1"
    ]
  },
  "0240SahnunIbnSacid.MudawwanaKubra": {
    "external_id": "",
    "genre_tags": [
      "GAL@fiqh",
      "CENT0200",
      "_FIQH",
      "GAL@0750-1000CE",
      "_HADITH",
      "_MALIKI",
      "GAL@literature-islamic",
      "GAL@period-classical",
      "GAL@literature-arabic",
      "GAL@malikis",
      "Shia@فقه المذهب المالكي",
      "JK@الفقه المالكي",
      "JK@كتب الفقه الإسلامي",
      "JK@كتب المصنفات والآثار",
      "Shamela@فقه مالكي"
    ],
    "relations": [],
    "title_ar": [
      "المدونة الكبرى",
      "المدونة"
    ],
    "title_lat": [
      "Mudawwana Kubra"
    ],
    "uri": "0240SahnunIbnSacid.MudawwanaKubra",
    "versions": [
      "0240SahnunIbnSacid.MudawwanaKubra.Shia000895Vols-ara1",
      "0240SahnunIbnSacid.MudawwanaKubra.JK000227-ara1",
      "0240SahnunIbnSacid.MudawwanaKubra.Shamela0000587-ara1"
    ]
  },
  "0241IbnHanbal.AhkamNisa": {
    "external_id": "",
    "genre_tags": [
      "GAL@nodata",
      "_FIQH",
      "CENT0300",
      "_HANBALI",
      "Shamela@فقه حنبلي"
    ],
    "relations": [],
    "title_ar": [
      "أحكم النساء",
      ""
    ],
    "title_lat": [
      "aḥkam al-nisāʾ",
      ""
    ],
    "uri": "0241IbnHanbal.AhkamNisa",
    "versions": [
      "0241IbnHanbal.AhkamNisa.Shamela0095563-ara1"
    ]
  },
  "0241IbnHanbal.AsamiWaKuna": {
    "external_id": "",
    "genre_tags": [
      "_TABAQAT",
      "GAL@nodata",
      "_TARAJIM",
      "_HADITH",
      "PPE",
      "CENT0300",
      "JK@التراجم العامة",
      "JK@كتب التراجم العامة",
      "JK@كتب الحديث النبوي الشريف وتراجم الرواة",
      "Shamela@التراجم والطبقات"
    ],
    "relations": [],
    "title_ar": [
      "الأسامي والكنى"
    ],
    "title_lat": [
      "al-Asāmī wa-l-kuná"
    ],
    "uri": "0241IbnHanbal.AsamiWaKuna",
    "versions": [
      "0241IbnHanbal.AsamiWaKuna.JK000525-ara1",
      "0241IbnHanbal.AsamiWaKuna.Shamela0005780-ara1"
    ]
  },
  "0241IbnHanbal.Ashriba": {
    "external_id": "",
    "genre_tags": [
      "ShamAY@بحوث ومسائل",
      "Shamela@بحوث ومسائل",
      "JK@الأجزاء الموضوعية",
      "JK@الفقه الحنبلي",
      "JK@كتب الفقه الإسلامي"
    ],
    "relations": [],
    "title_ar": [
      "الأشربة"
    ],
    "title_lat": [
      "al-Ašribaŧ"
    ],
    "uri": "0241IbnHanbal.Ashriba",
    "versions": [
      "0241IbnHanbal.Ashriba.ShamAY0034333-ara1",
      "0241IbnHanbal.Ashriba.Shamela0012995-ara2",
      "0241IbnHanbal.Ashriba.JK000673-ara1"
    ]
  },
  "0241IbnHanbal.CaqidaRiwayatKhallal": {
    "external_id": "",
    "genre_tags": [
      "GAL@nodata",
      "_MILAL",
      "_HADITH",
      "_CAQAID",
      "CENT0300",
      "Shamela@العقيدة",
      "JK@كتب العقائد المسندة",
      "JK@كتب العقائد والملل",
      "JK@مواضيع عقدية"
    ],
    "relations": [],
    "title_ar": [
      "العقيدة رواية أبي بكر الخلال",
      "العقيدة"
    ],
    "title_lat": [
      "Caqida Riwayat Khallal"
    ],
    "uri": "0241IbnHanbal.CaqidaRiwayatKhallal",
    "versions": [
      "0241IbnHanbal.CaqidaRiwayatKhallal.Shamela0006498-ara1",
      "0241IbnHanbal.CaqidaRiwayatKhallal.JK000323-ara1"
    ]
  },
  "0241IbnHanbal.CilalWaMacrifa": {
    "external_id": "",
    "genre_tags": [
      "_MAWDUC",
      "_SUNNI",
      "GAL@lesserschools",
      "GAL@fiqh",
      "_TARAJIM",
      "GAL@0750-1000CE",
      "GAL@period-classical",
      "_DACIF",
      "_HADITH",
      "_SUALAT",
      "_AHKAM",
      "GAL@literature-islamic",
      "_CILAL",
      "PPE",
      "CENT0300",
      "GAL@literature-arabic",
      "JK@العلل",
      "JK@كتب الأحاديث الضعيفة والموضوعة",
      "JK@كتب العلل والأحكام",
      "ShamAY@العلل والسؤالات",
      "Shia@أهم مصادر رجال الحديث عند السنة",
      "Shamela@العلل والسؤالات"
    ],
    "relations": [],
    "title_ar": [
      "العلل و معرفة الرجال"
    ],
    "title_lat": [
      "al-ʿIlal wa maʿrifaŧ al-riǧāl"
    ],
    "uri": "0241IbnHanbal.CilalWaMacrifa",
    "versions": [
      "0241IbnHanbal.CilalWaMacrifa.JK000521-ara1",
      "0241IbnHanbal.CilalWaMacrifa.ShamAY0034149-ara2",
      "0241IbnHanbal.CilalWaMacrifa.Shia003057Vols-ara1",
      "0241IbnHanbal.CilalWaMacrifa.Shamela0002331-ara1"
    ]
  },
  "0241IbnHanbal.FadailSahaba": {
    "external_id": "",
    "genre_tags": [
      "_ASHAB",
      "_TABAQAT",
      "GAL@lesserschools",
      "GAL@fiqh",
      "_TARAJIM",
      "GAL@0750-1000CE",
      "_SIRA",
      "_HADITH",
      "GAL@literature-islamic",
      "GAL@period-classical",
      "PPE",
      "CENT0300",
      "GAL@literature-arabic",
      "JK@السير والتاريخ",
      "JK@الطبقات والتراجم",
      "JK@سيرة أصحاب النبي",
      "JK@كتب سيرة النبي صلى الله عليه وسلم وأصحابه",
      "Shamela@متون الحديث"
    ],
    "relations": [],
    "title_ar": [
      "فضائل السحبة",
      ""
    ],
    "title_lat": [
      "faḍāʾil al-saḥabŧ",
      ""
    ],
    "uri": "0241IbnHanbal.FadailSahaba",
    "versions": [
      "0241IbnHanbal.FadailSahaba.JK000482-ara1",
      "0241IbnHanbal.FadailSahaba.Shamela0013136-ara1"
    ]
  },
  "0241IbnHanbal.JamicFiCilal": {
    "external_id": "",
    "genre_tags": [
      "_MAWDUC",
      "GAL@lesserschools",
      "GAL@fiqh",
      "GAL@0750-1000CE",
      "GAL@period-classical",
      "_DACIF",
      "_HADITH",
      "_SUALAT",
      "_AHKAM",
      "GAL@literature-islamic",
      "_CILAL",
      "CENT0300",
      "GAL@literature-arabic",
      "Shamela@العلل والسؤالات",
      "JK@العلل",
      "JK@كتب الأحاديث الضعيفة والموضوعة",
      "JK@كتب العلل والأحكام"
    ],
    "relations": [],
    "title_ar": [
      "من كلام الامام عبد الله أحمد بن حنبل في علل الحديث ومعرفة الرجال",
      ""
    ],
    "title_lat": [
      "Min kalām al-imām ʿAbd Allāh Aḥmad b. Ḥanbal fī ʿilal al-ḥadīṯ wa-maʿrifaŧ al-riǧāl",
      ""
    ],
    "uri": "0241IbnHanbal.JamicFiCilal",
    "versions": [
      "0241IbnHanbal.JamicFiCilal.Shamela0010272-ara2",
      "0241IbnHanbal.JamicFiCilal.Shamela0006044-ara1",
      "0241IbnHanbal.JamicFiCilal.JK000749-ara1"
    ]
  },
  "0241IbnHanbal.MasailRiwayatCabdAllah": {
    "external_id": "",
    "genre_tags": [
      "GAL@lesserschools",
      "GAL@fiqh",
      "_FIQH",
      "GAL@0750-1000CE",
      "_HANBALI",
      "GAL@literature-islamic",
      "GAL@period-classical",
      "CENT0300",
      "GAL@literature-arabic",
      "JK@الفقه الحنبلي",
      "JK@كتب الفقه الإسلامي",
      "Shamela@فقه حنبلي"
    ],
    "relations": [],
    "title_ar": [
      "مسائل الامام أحمد بن حنبل رواية ابنه عبد¶    الله بن أحمد",
      "مسائل الامام أحمد بن هنبل"
    ],
    "title_lat": [
      "Masāʾil al-imām Aḥmad b. Ḥanbal riwāyaŧ ibnihi ʿAbd¶    Allāh b. Aḥmad",
      "Masāʾil al-imām Aḥmad b. Hanbal"
    ],
    "uri": "0241IbnHanbal.MasailRiwayatCabdAllah",
    "versions": [
      "0241IbnHanbal.MasailRiwayatCabdAllah.JK001182-ara1",
      "0241IbnHanbal.MasailRiwayatCabdAllah.Shamela0006105-ara1"
    ]
  },
  "0241IbnHanbal.MasailRiwayatIbnHani": {
    "external_id": "",
    "genre_tags": [
      "ShamAY@فقه حنبلي"
    ],
    "relations": [],
    "title_ar": [
      "مسائل الإمام أبي عبد الله أحمد بن حنبل",
      "مسائل الإمام أبي عبد الله أحمد بن حنبل ",
      "مسائل أحمد بن حنبل رواية ابن هانئ - ط الفاروق الحديثة"
    ],
    "title_lat": [
      "Masail Riwayat Ibn Hani"
    ],
    "uri": "0241IbnHanbal.MasailRiwayatIbnHani",
    "versions": [
      "0241IbnHanbal.MasailRiwayatIbnHani.ShamAY0038134-ara1"
    ]
  },
  "0241IbnHanbal.MasailRiwayatSalih": {
    "external_id": "",
    "genre_tags": [
      "GAL@lesserschools",
      "GAL@fiqh",
      "_FIQH",
      "GAL@0750-1000CE",
      "_HANBALI",
      "GAL@literature-islamic",
      "GAL@period-classical",
      "CENT0300",
      "GAL@literature-arabic",
      "JK@الفقه الحنبلي",
      "JK@كتب الفقه الإسلامي",
      "ShamAY@فقه حنبلي",
      "Shamela@فقه حنبلي"
    ],
    "relations": [],
    "title_ar": [
      "مسائل الامام أحمد بن حنبل رواية ابن أبي ال¶    فضل صالح",
      "مسائل رواية صالح"
    ],
    "title_lat": [
      "Masāʾil al-imām Aḥmad b. Ḥanbal riwāyaŧ Ibn Abī al-¶    Faḍl Ṣāliḥ",
      "Masāʾil riwāyaŧ Ṣāliḥ"
    ],
    "uri": "0241IbnHanbal.MasailRiwayatSalih",
    "versions": [
      "0241IbnHanbal.MasailRiwayatSalih.JK001184-ara1",
      "0241IbnHanbal.MasailRiwayatSalih.ShamAY0034272-ara1",
      "0241IbnHanbal.MasailRiwayatSalih.Shamela0006106-ara1"
    ]
  },
  "0241IbnHanbal.MinSualatIbnMuhammadAthram": {
    "external_id": "",
    "genre_tags": [
      "GAL@lesserschools",
      "GAL@fiqh",
      "_CILAL",
      "GAL@0750-1000CE",
      "_SUALAT",
      "GAL@literature-islamic",
      "GAL@period-classical",
      "CENT0300",
      "GAL@literature-arabic",
      "Shamela@العلل والسؤالات"
    ],
    "relations": [],
    "title_ar": [
      "سؤلات أبي بكر الأثرم",
      ""
    ],
    "title_lat": [
      "suʾalāt abī bakr al-aṯram",
      ""
    ],
    "uri": "0241IbnHanbal.MinSualatIbnMuhammadAthram",
    "versions": [
      "0241IbnHanbal.MinSualatIbnMuhammadAthram.Shamela0025873-ara1"
    ]
  },
  "0241IbnHanbal.Musnad": {
    "external_id": "",
    "genre_tags": [
      "_MASANID",
      "_MACAJIM",
      "_SUNNI",
      "GAL@lesserschools",
      "GAL@fiqh",
      "_FIQH",
      "_TARAJIM",
      "GAL@0750-1000CE",
      "_HADITH",
      "GAL@literature-islamic",
      "GAL@period-classical",
      "CENT0300",
      "GAL@literature-arabic",
      "Shia@مصادر الحديث السنية ـ قسم الفقه",
      "Shamela@متون الحديث",
      "ShamAY@متون الحديث - مرقم آليا",
      "JK@المسانيد والمعاجم",
      "JK@كتب الحديث النبوي الشريف وتراجم الرواة",
      "ShamAY@متون الحديث"
    ],
    "relations": [],
    "title_ar": [
      "مسند"
    ],
    "title_lat": [
      "Musnad"
    ],
    "uri": "0241IbnHanbal.Musnad",
    "versions": [
      "0241IbnHanbal.Musnad.Shia001707Vols-ara6",
      "0241IbnHanbal.Musnad.Shamela0025794-ara1",
      "0241IbnHanbal.Musnad.Shamela0098139-ara3",
      "0241IbnHanbal.Musnad.Shamela0013157-ara1",
      "0241IbnHanbal.Musnad.ShamAY0033936-ara4",
      "0241IbnHanbal.Musnad.JK000145-ara2",
      "0241IbnHanbal.Musnad.ShamAY0033964-ara2",
      "0241IbnHanbal.Musnad.ShamAY0033963-ara5"
    ]
  },
  "0241IbnHanbal.RaddCalaZanadiqa": {
    "external_id": "",
    "genre_tags": [
      "GAL@lesserschools",
      "GAL@fiqh",
      "GAL@0750-1000CE",
      "_MILAL",
      "_HADITH",
      "_CAQAID",
      "_RUDUD",
      "GAL@literature-islamic",
      "GAL@period-classical",
      "_AJZA",
      "CENT0300",
      "GAL@literature-arabic",
      "JK@الأجزاء الموضوعية",
      "JK@كتب الردود",
      "JK@كتب العقائد المسندة",
      "JK@كتب العقائد والملل",
      "Shamela@العقيدة"
    ],
    "relations": [],
    "title_ar": [
      "الرد على الزنادقة والجهمية",
      "الرد على الجهمية والزنادقة"
    ],
    "title_lat": [
      "Radd Cala Zanadiqa"
    ],
    "uri": "0241IbnHanbal.RaddCalaZanadiqa",
    "versions": [
      "0241IbnHanbal.RaddCalaZanadiqa.JK000341-ara1",
      "0241IbnHanbal.RaddCalaZanadiqa.Shamela0007623-ara1"
    ]
  },
  "0241IbnHanbal.Salat": {
    "external_id": "",
    "genre_tags": [
      "ShamAY@الأجزاء الحديثية - مرقم آليا"
    ],
    "relations": [],
    "title_ar": [
      "الصلاة للإمام أحمد ",
      "الصلاة للامام أحمد",
      "الصلاة للإمام أحمد"
    ],
    "title_lat": [
      "Salat"
    ],
    "uri": "0241IbnHanbal.Salat",
    "versions": [
      "0241IbnHanbal.Salat.ShamAY0035233-ara1"
    ]
  },
  "0241IbnHanbal.SualatAbiDawudLiIbnHanbal": {
    "external_id": "",
    "genre_tags": [
      "GAL@lesserschools",
      "GAL@fiqh",
      "_TARAJIM",
      "GAL@0750-1000CE",
      "GAL@period-classical",
      "_HADITH",
      "_SUALAT",
      "GAL@literature-islamic",
      "_CILAL",
      "CENT0300",
      "GAL@literature-arabic",
      "Shamela@العلل والسؤالات",
      "JK@السؤالات",
      "JK@كتب الحديث النبوي الشريف وتراجم الرواة"
    ],
    "relations": [],
    "title_ar": [
      "سؤلات أبي داود للامام أحمد بن حنبل",
      "سؤلات أبي داود"
    ],
    "title_lat": [
      "suʾalāt abī dāwud li-l-imām aḥmad b. ḥanbal",
      "suʾalāt abī dāwud"
    ],
    "uri": "0241IbnHanbal.SualatAbiDawudLiIbnHanbal",
    "versions": [
      "0241IbnHanbal.SualatAbiDawudLiIbnHanbal.Shamela0005945-ara1",
      "0241IbnHanbal.SualatAbiDawudLiIbnHanbal.JK000709-ara1"
    ]
  },
  "0241IbnHanbal.UsulSunna": {
    "external_id": "",
    "genre_tags": [
      "GAL@lesserschools",
      "GAL@fiqh",
      "GAL@0750-1000CE",
      "_MILAL",
      "_HADITH",
      "_CAQAID",
      "GAL@literature-islamic",
      "GAL@period-classical",
      "_AJZA",
      "CENT0300",
      "GAL@literature-arabic",
      "Shamela@العقيدة",
      "JK@الأجزاء الموضوعية",
      "JK@كتب العقائد المسندة",
      "JK@كتب العقائد والملل"
    ],
    "relations": [],
    "title_ar": [
      "أصول السنة"
    ],
    "title_lat": [
      "Usul Sunna"
    ],
    "uri": "0241IbnHanbal.UsulSunna",
    "versions": [
      "0241IbnHanbal.UsulSunna.Shamela0006418-ara1",
      "0241IbnHanbal.UsulSunna.JK000354-ara1"
    ]
  },
  "0241IbnHanbal.Zuhd": {
    "external_id": "",
    "genre_tags": [
      "_AKHLAQ",
      "GAL@lesserschools",
      "GAL@fiqh",
      "GAL@0750-1000CE",
      "_HADITH",
      "GAL@literature-islamic",
      "GAL@period-classical",
      "_AJZA",
      "CENT0300",
      "GAL@literature-arabic",
      "JK@الأجزاء الموضوعية",
      "JK@الكتب المسندة",
      "JK@كتب الأخلاق والسلوك",
      "JK@مواضيع مسندة في الأخلاق والتزكية",
      "Shamela@الرقاق والآداب والأذكار",
      "ShamAY@الرقاق والآداب والأذكار"
    ],
    "relations": [],
    "title_ar": [
      "الزهد"
    ],
    "title_lat": [
      "al-Zuhd"
    ],
    "uri": "0241IbnHanbal.Zuhd",
    "versions": [
      "0241IbnHanbal.Zuhd.JK000084-ara2",
      "0241IbnHanbal.Zuhd.Shamela0008494-ara1",
      "0241IbnHanbal.Zuhd.ShamAY0033738-ara3"
    ]
  },
  "0242IbnAslamTusi.Arbacun": {
    "external_id": "",
    "genre_tags": [
      "_HADITH",
      "_AJZA",
      "GAL@nodata",
      "Shamela@الأجزاء الحديثية"
    ],
    "relations": [],
    "title_ar": [
      "الأربعون"
    ],
    "title_lat": [
      "Arbacun"
    ],
    "uri": "0242IbnAslamTusi.Arbacun",
    "versions": [
      "0242IbnAslamTusi.Arbacun.Shamela0010620-ara1"
    ]
  },
  "0243HannadIbnSari.Zuhd": {
    "external_id": "",
    "genre_tags": [
      "_ADAB",
      "_AKHLAQ",
      "GAL@hadith",
      "_RAQAIQ",
      "GAL@0750-1000CE",
      "_HADITH",
      "GAL@literature-islamic",
      "GAL@period-classical",
      "_AJZA",
      "CENT0300",
      "GAL@literature-arabic",
      "_ADHKAR",
      "JK@الأجزاء الموضوعية",
      "JK@الكتب المسندة",
      "JK@كتب الأخلاق والسلوك",
      "JK@مواضيع مسندة في الأخلاق والتزكية",
      "Shamela@الرقاق والآداب والأذكار"
    ],
    "relations": [],
    "title_ar": [
      "الزهد",
      "الزهد لابن السري"
    ],
    "title_lat": [
      "Zuhd"
    ],
    "uri": "0243HannadIbnSari.Zuhd",
    "versions": [
      "0243HannadIbnSari.Zuhd.JK000085-ara1",
      "0243HannadIbnSari.Zuhd.Shamela0013027-ara1"
    ]
  },
  "0243HarithMuhasibi.AdabNufus": {
    "external_id": "",
    "genre_tags": [
      "_ADAB",
      "_AKHLAQ",
      "GAL@sufism",
      "_RAQAIQ",
      "GAL@mysticism",
      "GAL@0750-1000CE",
      "_MISC",
      "_SULUK",
      "GAL@literature-islamic",
      "GAL@period-classical",
      "CENT0300",
      "GAL@literature-arabic",
      "_ADHKAR",
      "Shamela@الرقاق والآداب والأذكار",
      "JK@كتب أخرى",
      "JK@كتب الأخلاق والسلوك",
      "JK@كتب متفرقة في الأخلاق والسلوك",
      "JK@متفرقات"
    ],
    "relations": [],
    "title_ar": [
      "آداب النفوس",
      "أداب النفوس"
    ],
    "title_lat": [
      "Adab Nufus"
    ],
    "uri": "0243HarithMuhasibi.AdabNufus",
    "versions": [
      "0243HarithMuhasibi.AdabNufus.Shamela0006853-ara1",
      "0243HarithMuhasibi.AdabNufus.JK000850-ara1"
    ]
  },
  "0243HarithMuhasibi.FahmQuran": {
    "external_id": "",
    "genre_tags": [
      "_CULUM",
      "_TAFSIR",
      "GAL@nodata",
      "_QURAN",
      "CENT0300",
      "Shamela@علوم القرآن",
      "JK@علوم القرآن",
      "JK@كتب التفاسير وعلوم القرآن",
      "JK@مواضيع في علوم القرآن"
    ],
    "relations": [],
    "title_ar": [
      "فهم القرآن ومعانيه",
      "فهم القرآن"
    ],
    "title_lat": [
      "Fahm Quran"
    ],
    "uri": "0243HarithMuhasibi.FahmQuran",
    "versions": [
      "0243HarithMuhasibi.FahmQuran.Shamela0005550-ara1",
      "0243HarithMuhasibi.FahmQuran.JK000446-ara1"
    ]
  },
  "0243HarithMuhasibi.MaiyyatCaql": {
    "external_id": "",
    "genre_tags": [
      "GAL@sufism",
      "GAL@mysticism",
      "GAL@0750-1000CE",
      "_MILAL",
      "_CAQAID",
      "GAL@literature-islamic",
      "GAL@period-classical",
      "CENT0300",
      "GAL@literature-arabic",
      "Shamela@العقيدة",
      "JK@كتب العقائد والملل",
      "JK@مواضيع عقدية",
      "JK@مواضيع عقدية محددة"
    ],
    "relations": [],
    "title_ar": [
      "مائية العقل ومعناه واختلاف الناس فيه",
      "ماهية العقل ومعناه واختلاف الناس فيه"
    ],
    "title_lat": [
      "Māʾiyyaŧ al-ʿaql wa-maʿnāhu wa-iḫtilāf al-nās fīhi",
      "Māhiyyaŧ al-ʿaql wa-maʿnāhu wa-iḫtilāf al-nās fīhi"
    ],
    "uri": "0243HarithMuhasibi.MaiyyatCaql",
    "versions": [
      "0243HarithMuhasibi.MaiyyatCaql.Shamela0006492-ara1",
      "0243HarithMuhasibi.MaiyyatCaql.JK000802-ara1"
    ]
  },
  "0243HarithMuhasibi.Makasib": {
    "external_id": "",
    "genre_tags": [
      "GAL@sufism",
      "_FIQH",
      "GAL@mysticism",
      "_BUHUTH",
      "_MASAIL",
      "GAL@0750-1000CE",
      "GAL@literature-islamic",
      "GAL@period-classical",
      "_AJZA",
      "CENT0300",
      "GAL@literature-arabic",
      "JK@الأجزاء الموضوعية",
      "JK@كتب الفقه الإسلامي",
      "JK@مسائل فقهية",
      "Shamela@بحوث ومسائل"
    ],
    "relations": [],
    "title_ar": [
      "المكاسب والورع والشبهة وبيان مباحها ومحظورها واختلاف الناس في طلبها والرد على الغالطين فيه",
      "المكاسب"
    ],
    "title_lat": [
      "Makasib"
    ],
    "uri": "0243HarithMuhasibi.Makasib",
    "versions": [
      "0243HarithMuhasibi.Makasib.JK001158-ara1",
      "0243HarithMuhasibi.Makasib.Shamela0006230-ara1"
    ]
  },
  "0243HarithMuhasibi.Ricaya": {
    "external_id": "",
    "genre_tags": [],
    "relations": [],
    "title_ar": [],
    "title_lat": [
      "Ricaya"
    ],
    "uri": "0243HarithMuhasibi.Ricaya",
    "versions": [
      "0243HarithMuhasibi.Ricaya.Kraken2107192213391-ara1"
    ]
  },
  "0243HarithMuhasibi.RisalatMustarshidin": {
    "external_id": "",
    "genre_tags": [
      "_ADAB",
      "_AKHLAQ",
      "GAL@sufism",
      "_RAQAIQ",
      "GAL@mysticism",
      "GAL@0750-1000CE",
      "_MISC",
      "_SULUK",
      "GAL@literature-islamic",
      "GAL@period-classical",
      "CENT0300",
      "GAL@literature-arabic",
      "_ADHKAR",
      "JK@كتب أخرى",
      "JK@كتب الأخلاق والسلوك",
      "JK@كتب متفرقة في الأخلاق والسلوك",
      "Shamela@الرقاق والآداب والأذكار"
    ],
    "relations": [],
    "title_ar": [
      "رسالة المسترشدين"
    ],
    "title_lat": [
      "Risalat Mustarshidin"
    ],
    "uri": "0243HarithMuhasibi.RisalatMustarshidin",
    "versions": [
      "0243HarithMuhasibi.RisalatMustarshidin.JK001219-ara1",
      "0243HarithMuhasibi.RisalatMustarshidin.Shamela0006871-ara1"
    ]
  },
  "0243HarithMuhasibi.Tawahhum": {
    "external_id": "",
    "genre_tags": [
      "_ADAB",
      "GAL@sufism",
      "_RAQAIQ",
      "GAL@mysticism",
      "GAL@0750-1000CE",
      "GAL@literature-islamic",
      "GAL@period-classical",
      "CENT0300",
      "GAL@literature-arabic",
      "_ADHKAR",
      "Shamela@الرقاق والآداب والأذكار"
    ],
    "relations": [],
    "title_ar": [
      "التوهم في وصف أحوال الآخرة"
    ],
    "title_lat": [
      "Tawahhum"
    ],
    "uri": "0243HarithMuhasibi.Tawahhum",
    "versions": [
      "0243HarithMuhasibi.Tawahhum.Shamela0021799-ara1"
    ]
  },
  "0243HarithMuhasibi.Wasaya": {
    "external_id": "",
    "genre_tags": [],
    "relations": [],
    "title_ar": [],
    "title_lat": [
      "Wasaya"
    ],
    "uri": "0243HarithMuhasibi.Wasaya",
    "versions": [
      "0243HarithMuhasibi.Wasaya.Kraken22021817402400-ara1"
    ]
  },
  "0243IbnYahyaCadani.Iman": {
    "external_id": "",
    "genre_tags": [
      "_SUNNI",
      "GAL@nodata",
      "_MILAL",
      "_HADITH",
      "_CAQAID",
      "_AJZA",
      "CENT0300",
      "Shamela@الأجزاء الحديثية",
      "Shia@مصادر الحديث السنية ـ القسم العام",
      "JK@الأجزاء الموضوعية",
      "JK@كتب العقائد المسندة",
      "JK@كتب العقائد والملل"
    ],
    "relations": [],
    "title_ar": [
      "الإيمان للعدني",
      "كتاب الإيمان"
    ],
    "title_lat": [
      "Iman"
    ],
    "uri": "0243IbnYahyaCadani.Iman",
    "versions": [
      "0243IbnYahyaCadani.Iman.Shamela0013006-ara1",
      "0243IbnYahyaCadani.Iman.Shia001918-ara1",
      "0243IbnYahyaCadani.Iman.JK000321-ara1"
    ]
  },
  "0243YuhannaIbnMasawayh.NawadirTibbiyya": {
    "external_id": "",
    "genre_tags": [],
    "relations": [],
    "title_ar": [],
    "title_lat": [
      "Nawadir Tibbiyya"
    ],
    "uri": "0243YuhannaIbnMasawayh.NawadirTibbiyya",
    "versions": [
      "0243YuhannaIbnMasawayh.NawadirTibbiyya.ALCorpus00031-ara1"
    ]
  },
  "0244IbnSikkit.Alfaz": {
    "external_id": "",
    "genre_tags": [
      "Sham@الغريب والمعاجم ولغة الفقه"
    ],
    "relations": [],
    "title_ar": [
      "كتاب الألفاظ لابن السكيت",
      "كتاب الألفاظ (أقدم معجم في المعاني)"
    ],
    "title_lat": [
      "Alfaz"
    ],
    "uri": "0244IbnSikkit.Alfaz",
    "versions": [
      "0244IbnSikkit.Alfaz.Sham19Y0013249-ara1"
    ]
  },
  "0244IbnSikkit.IslahMantiq": {
    "external_id": "",
    "genre_tags": [
      "_ADAB",
      "_MUSTALAHAT",
      "_NAHW",
      "GAL@0750-1000CE",
      "_LUGHA",
      "_SARF",
      "GAL@philology",
      "GAL@literature-islamic",
      "GAL@period-classical",
      "CENT0300",
      "GAL@literature-arabic",
      "Shamela@كتب اللغة",
      "ShamAY@كتب اللغة",
      "JK@الإصلاح اللغوي",
      "JK@التصحيح اللغوي",
      "JK@كتب الأدب"
    ],
    "relations": [],
    "title_ar": [
      "إصلاح المنطق",
      "اصلاح المنطق",
      "إصلاح المنطق (ط المعارف)"
    ],
    "title_lat": [
      "Islah Mantiq"
    ],
    "uri": "0244IbnSikkit.IslahMantiq",
    "versions": [
      "0244IbnSikkit.IslahMantiq.Shamela0007508-ara1",
      "0244IbnSikkit.IslahMantiq.ShamAY0034670-ara1",
      "0244IbnSikkit.IslahMantiq.JK001170-ara2"
    ]
  },
  "0244IbnSikkit.KanzLughawi": {
    "external_id": "",
    "genre_tags": [
      "_MACAJIM",
      "_GHARIB",
      "_MUSTALAHAT",
      "_FIQH",
      "_NAHW",
      "_MASAIL",
      "GAL@0750-1000CE",
      "_LUGHA",
      "_SARF",
      "GAL@philology",
      "GAL@literature-islamic",
      "GAL@period-classical",
      "CENT0300",
      "GAL@literature-arabic",
      "Shia@علوم اللغة العربية",
      "JK@كتب المعاجم والغريب والمصطلحات",
      "JK@مسائل في الغريب والمعاني",
      "Shamela@الغريب والمعاجم ولغة الفقه"
    ],
    "relations": [],
    "title_ar": [
      "الكنز اللغوي",
      "الكنز اللغوي في اللسن العربي"
    ],
    "title_lat": [
      "Kanz Lughawi"
    ],
    "uri": "0244IbnSikkit.KanzLughawi",
    "versions": [
      "0244IbnSikkit.KanzLughawi.Shia003899-ara1",
      "0244IbnSikkit.KanzLughawi.JK010885-ara1",
      "0244IbnSikkit.KanzLughawi.Shamela0008533-ara1"
    ]
  },
  "0244IbnSikkit.QalbWaIbdal": {
    "external_id": "",
    "genre_tags": [
      "GAL@0750-1000CE",
      "_LUGHA",
      "GAL@philology",
      "GAL@literature-islamic",
      "GAL@period-classical",
      "CENT0300",
      "GAL@literature-arabic",
      "Shamela@كتب اللغة - مرقم آليا"
    ],
    "relations": [],
    "title_ar": [
      "القلب والإبدال"
    ],
    "title_lat": [
      "Qalb Wa Ibdal"
    ],
    "uri": "0244IbnSikkit.QalbWaIbdal",
    "versions": [
      "0244IbnSikkit.QalbWaIbdal.Shamela0005420-ara1"
    ]
  },
  "0245IbnKullab.Maqalat": {
    "external_id": "",
    "genre_tags": [],
    "relations": [],
    "title_ar": [
      "مقالات"
    ],
    "title_lat": [
      "Maqālāt"
    ],
    "uri": "0245IbnKullab.Maqalat",
    "versions": [
      "0245IbnKullab.Maqalat.AOCP20251104002-ara1"
    ]
  },
  "0245LuwaynMissisi.JuzHadith": {
    "external_id": "",
    "genre_tags": [
      "GAL@nodata",
      "_TARAJIM",
      "_HADITH",
      "_AJZA",
      "CENT0300",
      "Shamela@الأجزاء الحديثية",
      "Shamela@مخطوطات حديثية",
      "JK@أجزاء حديثية",
      "JK@الأجزاء المسندة",
      "JK@كتب الحديث النبوي الشريف وتراجم الرواة"
    ],
    "relations": [],
    "title_ar": [
      "جزء فيه حديث المصيصي لوين",
      "حديث لوين المصيصي",
      "حديث المصيصي لوين"
    ],
    "title_lat": [
      "Juz Hadith"
    ],
    "uri": "0245LuwaynMissisi.JuzHadith",
    "versions": [
      "0245LuwaynMissisi.JuzHadith.Shamela0001459-ara1",
      "0245LuwaynMissisi.JuzHadith.Shamela0029848-ara1",
      "0245LuwaynMissisi.JuzHadith.JK001186-ara1"
    ]
  },
  "0245MuhammadIbnHabib.KhalqInsan": {
    "external_id": "",
    "genre_tags": [],
    "relations": [],
    "title_ar": [
      "خلق الانسان في اللغة",
      ""
    ],
    "title_lat": [
      "Ḫalq al-insān fī al-luġaŧ",
      ""
    ],
    "uri": "0245MuhammadIbnHabib.KhalqInsan",
    "versions": [
      "0245MuhammadIbnHabib.KhalqInsan.Kraken21052117-ara1"
    ]
  },
  "0245MuhammadIbnHabib.ManNusibaLiUmmihi": {
    "external_id": "",
    "genre_tags": [
      "ShamAY@التراجم والطبقات - مرقم آليا"
    ],
    "relations": [],
    "title_ar": [
      "من نسب لأمه من الشعراء",
      "من نسب لأمه من الشعراء ",
      "من نسب لأمه من الشعراء لابن حبيب"
    ],
    "title_lat": [
      "Man Nusiba Li Ummihi"
    ],
    "uri": "0245MuhammadIbnHabib.ManNusibaLiUmmihi",
    "versions": [
      "0245MuhammadIbnHabib.ManNusibaLiUmmihi.ShamAY0035784-ara1"
    ]
  },
  "0245MuhammadIbnHabib.Muhabbar": {
    "external_id": "",
    "genre_tags": [
      "_FASAHA",
      "_ADAB",
      "CENT0300",
      "_TARIKH",
      "GAL@0750-1000CE",
      "GAL@philology",
      "GAL@literature-islamic",
      "GAL@period-classical",
      "_BALAGHA",
      "GAL@literature-arabic",
      "Shia@مصادر التاريخ",
      "JK@البلاغة والفصاحة",
      "JK@كتب الأدب",
      "Shamela@التاريخ"
    ],
    "relations": [],
    "title_ar": [
      "كتاب المحبر",
      "المحبر"
    ],
    "title_lat": [
      "kitāb al-muḥabbar",
      "al-muḥabbar"
    ],
    "uri": "0245MuhammadIbnHabib.Muhabbar",
    "versions": [
      "0245MuhammadIbnHabib.Muhabbar.Shia003457-ara1",
      "0245MuhammadIbnHabib.Muhabbar.JK011200-ara1",
      "0245MuhammadIbnHabib.Muhabbar.Shamela0012205-ara1"
    ]
  },
  "0245MuhammadIbnHabib.MukhtalafQabail": {
    "external_id": "",
    "genre_tags": [
      "_BULDAN",
      "_TARIKH",
      "GAL@0750-1000CE",
      "GAL@philology",
      "_ANSAB",
      "GAL@literature-islamic",
      "GEN",
      "GAL@period-classical",
      "PPE",
      "CENT0300",
      "GAL@literature-arabic",
      "Shamela@الأنساب",
      "JK@تواريخ البلدان والعوائل",
      "JK@كتب التاريخ"
    ],
    "relations": [],
    "title_ar": [
      "مختلف القبائل ومؤتلفها"
    ],
    "title_lat": [
      "Mukhtalaf Qabail"
    ],
    "uri": "0245MuhammadIbnHabib.MukhtalafQabail",
    "versions": [
      "0245MuhammadIbnHabib.MukhtalafQabail.Shamela0026540-ara1",
      "0245MuhammadIbnHabib.MukhtalafQabail.JK010501-ara1"
    ]
  },
  "0245MuhammadIbnHabib.MunammaqFiAkhbarQuraysh": {
    "external_id": "",
    "genre_tags": [
      "_BULDAN",
      "_TARIKH",
      "GAL@0750-1000CE",
      "GAL@philology",
      "GAL@literature-islamic",
      "GAL@period-classical",
      "CENT0300",
      "GAL@literature-arabic",
      "Shia@مصادر التاريخ",
      "JK@تواريخ البلدان والعوائل",
      "JK@كتب التاريخ",
      "Shamela@التاريخ"
    ],
    "relations": [],
    "title_ar": [
      "كتاب المنمق",
      "المنمق في أخبار قريش"
    ],
    "title_lat": [
      "Munammaq Fi Akhbar Quraysh"
    ],
    "uri": "0245MuhammadIbnHabib.MunammaqFiAkhbarQuraysh",
    "versions": [
      "0245MuhammadIbnHabib.MunammaqFiAkhbarQuraysh.Shia003458-ara1",
      "0245MuhammadIbnHabib.MunammaqFiAkhbarQuraysh.JK009275-ara1",
      "0245MuhammadIbnHabib.MunammaqFiAkhbarQuraysh.Shamela0012212-ara1"
    ]
  },
  "0245MuhammadIbnHabib.UmmahatNabi": {
    "external_id": "",
    "genre_tags": [
      "_HADITH",
      "_AJZA",
      "CENT0300",
      "GAL@nodata",
      "Shamela@الأجزاء الحديثية"
    ],
    "relations": [],
    "title_ar": [
      "أمهات النبي صلى الله عليه وسلم"
    ],
    "title_lat": [
      "Ummahat Nabi"
    ],
    "uri": "0245MuhammadIbnHabib.UmmahatNabi",
    "versions": [
      "0245MuhammadIbnHabib.UmmahatNabi.Shamela0026929-ara1"
    ]
  },
  "0246AbuCaliIbnShadhdhan.Hadith": {
    "external_id": "",
    "genre_tags": [
      "Shamela@مخطوطات حديثية"
    ],
    "relations": [],
    "title_ar": [
      "حديث ابن شاذان",
      "أجزاء ابن شاذان"
    ],
    "title_lat": [
      "Ḥadīṯ Ibn Šāḏān",
      "Aǧzāʾ Ibn Šāḏān"
    ],
    "uri": "0246AbuCaliIbnShadhdhan.Hadith",
    "versions": [
      "0246AbuCaliIbnShadhdhan.Hadith.Shamela0029847Vols-ara1"
    ]
  },
  "0246AhmadDawraqi.MusnadSacdIbnAbiWaqqas": {
    "external_id": "",
    "genre_tags": [
      "_MASANID",
      "_MACAJIM",
      "_SUNNI",
      "GAL@nodata",
      "_TARAJIM",
      "_HADITH",
      "_AJZA",
      "CENT0300",
      "JK@المسانيد والمعاجم",
      "JK@كتب الحديث النبوي الشريف وتراجم الرواة",
      "Shamela@الأجزاء الحديثية",
      "Shia@مصادر الحديث السنية ـ القسم العام"
    ],
    "relations": [],
    "title_ar": [
      "مسند سعد بن أبي وقاص",
      "مسند سعد"
    ],
    "title_lat": [
      "Musnad Sacd Ibn Abi Waqqas"
    ],
    "uri": "0246AhmadDawraqi.MusnadSacdIbnAbiWaqqas",
    "versions": [
      "0246AhmadDawraqi.MusnadSacdIbnAbiWaqqas.JK000642-ara1",
      "0246AhmadDawraqi.MusnadSacdIbnAbiWaqqas.Shamela0013166-ara1",
      "0246AhmadDawraqi.MusnadSacdIbnAbiWaqqas.Shia001919-ara1"
    ]
  },
  "0246DhuNunAbuFayd.Hadith": {
    "external_id": "",
    "genre_tags": [
      "_HADITH",
      "CENT0300",
      "_MAKHTUTAT",
      "GAL@nodata",
      "Shamela@مخطوطات حديثية"
    ],
    "relations": [],
    "title_ar": [
      "حديث ذي النون المصري"
    ],
    "title_lat": [
      "Hadith"
    ],
    "uri": "0246DhuNunAbuFayd.Hadith",
    "versions": [
      "0246DhuNunAbuFayd.Hadith.Shamela0030738-ara1"
    ]
  },
  "0246DicbilKhuzaci.Diwan": {
    "external_id": "",
    "genre_tags": [
      "ShamAY@الدواوين الشعرية - مرقم آليا",
      "JK@دواوين الشعر العربي",
      "JK@عباسي"
    ],
    "relations": [],
    "title_ar": [
      "ديوان دعبل بن علي ",
      "ديوان دعبل بن علي"
    ],
    "title_lat": [
      "Diwan"
    ],
    "uri": "0246DicbilKhuzaci.Diwan",
    "versions": [
      "0246DicbilKhuzaci.Diwan.ShamAY0037947-ara1",
      "0246DicbilKhuzaci.Diwan.JK007615-ara1"
    ]
  },
  "0246DicbilKhuzaci.WasayaMuluk": {
    "external_id": "",
    "genre_tags": [
      "_ADAB",
      "CENT0300",
      "GAL@nodata",
      "_SIYASA",
      "_BALAGHA",
      "Shamela@الأدب والبلاغة - مرقم آليا",
      "JK@كتب التراث السياسي"
    ],
    "relations": [],
    "title_ar": [
      "وصايا الملوك وأبناء الملوك من ولد قحطان بن هود",
      "وصايا الملوك"
    ],
    "title_lat": [
      "Wasaya Muluk"
    ],
    "uri": "0246DicbilKhuzaci.WasayaMuluk",
    "versions": [
      "0246DicbilKhuzaci.WasayaMuluk.Shamela0000741-ara1",
      "0246DicbilKhuzaci.WasayaMuluk.JK010741-ara1"
    ]
  },
  "0246HishamSulami.CawaliMalik": {
    "external_id": "",
    "genre_tags": [
      "_HADITH",
      "_AJZA",
      "CENT0300",
      "GAL@nodata",
      "Shamela@الأجزاء الحديثية"
    ],
    "relations": [],
    "title_ar": [
      "عوالي مالك رواية هشام بن عمار"
    ],
    "title_lat": [
      "Cawali Malik"
    ],
    "uri": "0246HishamSulami.CawaliMalik",
    "versions": [
      "0246HishamSulami.CawaliMalik.Shamela0026754-ara1"
    ]
  },
  "0246HishamSulami.HadithHisham": {
    "external_id": "",
    "genre_tags": [
      "GAL@nodata",
      "_TARAJIM",
      "_MISC",
      "_HADITH",
      "_AJZA",
      "CENT0300",
      "Shamela@الأجزاء الحديثية",
      "JK@أجزاء حديثية",
      "JK@أخرى",
      "JK@كتب الحديث النبوي الشريف وتراجم الرواة"
    ],
    "relations": [],
    "title_ar": [
      "حديث هشام بن عمار"
    ],
    "title_lat": [
      "Hadith Hisham"
    ],
    "uri": "0246HishamSulami.HadithHisham",
    "versions": [
      "0246HishamSulami.HadithHisham.Shamela0013112-ara1",
      "0246HishamSulami.HadithHisham.JK007106-ara1"
    ]
  },
  "0246HusaynMarwazi.BirrWaSila": {
    "external_id": "",
    "genre_tags": [
      "GAL@polyhistors",
      "_AKHLAQ",
      "GAL@counsel",
      "GAL@0750-1000CE",
      "GAL@homiletics",
      "_HADITH",
      "GAL@encyclopaedias",
      "GAL@literature-islamic",
      "GAL@period-classical",
      "_AJZA",
      "CENT0300",
      "GAL@literature-arabic",
      "Shamela@متون الحديث",
      "JK@الأجزاء الموضوعية",
      "JK@الكتب المسندة",
      "JK@كتب الأخلاق والسلوك",
      "JK@مواضيع مسندة في الأخلاق والتزكية"
    ],
    "relations": [],
    "title_ar": [
      "البر والصلة (عن ابن المبارك وغيره)",
      "البر والصلة"
    ],
    "title_lat": [
      "Birr Wa Sila"
    ],
    "uri": "0246HusaynMarwazi.BirrWaSila",
    "versions": [
      "0246HusaynMarwazi.BirrWaSila.Shamela0013007-ara1",
      "0246HusaynMarwazi.BirrWaSila.JK000033-ara1"
    ]
  },
  "0246IbnCumarDuri.JuzFihiQiraat": {
    "external_id": "",
    "genre_tags": [
      "_CULUM",
      "_TAFSIR",
      "GAL@nodata",
      "_QIRAAT",
      "_HADITH",
      "_QURAN",
      "_AJZA",
      "CENT0300",
      "JK@الأجزاء الموضوعية",
      "JK@القراءات",
      "JK@علوم القرآن",
      "JK@كتب التفاسير وعلوم القرآن",
      "Shamela@الأجزاء الحديثية"
    ],
    "relations": [],
    "title_ar": [
      "جزء فيه قراءات النبي",
      "جزء فيه قراءات النبي صلى الله عليه وسلم"
    ],
    "title_lat": [
      "Juz Fihi Qiraat"
    ],
    "uri": "0246IbnCumarDuri.JuzFihiQiraat",
    "versions": [
      "0246IbnCumarDuri.JuzFihiQiraat.JK001122-ara1",
      "0246IbnCumarDuri.JuzFihiQiraat.Shamela0013106-ara1"
    ]
  },
  "0246QasimRassi.CadlWaTawhid": {
    "external_id": "",
    "genre_tags": [
      "Zaydiyya@مجاميع أئمة أهل البيت"
    ],
    "relations": [
      {
        "dest": "0246QasimRassi.Majmuc",
        "main_rel_type": "PART",
        "sec_rel_type": "",
        "source": "0246QasimRassi.CadlWaTawhid"
      }
    ],
    "title_ar": [
      "العدل والتوحيد"
    ],
    "title_lat": [
      "al-ʿAdl wa-al-tawḥīd"
    ],
    "uri": "0246QasimRassi.CadlWaTawhid",
    "versions": [
      "0246QasimRassi.CadlWaTawhid.Zaydiyya0000075BK7-ara1",
      "0246QasimRassi.CadlWaTawhid.Rafed0003477VolsBK10-ara2"
    ]
  },
  "0246QasimRassi.CalimWaWafid": {
    "external_id": "",
    "genre_tags": [
      "Zaydiyya@مجاميع أئمة أهل البيت"
    ],
    "relations": [
      {
        "dest": "0246QasimRassi.Majmuc",
        "main_rel_type": "PART",
        "sec_rel_type": "",
        "source": "0246QasimRassi.CalimWaWafid"
      }
    ],
    "title_ar": [
      "العالم والوافد"
    ],
    "title_lat": [
      "al-ʿĀlim wa-al-wāfid"
    ],
    "uri": "0246QasimRassi.CalimWaWafid",
    "versions": [
      "0246QasimRassi.CalimWaWafid.Zaydiyya0000075BK27-ara1",
      "0246QasimRassi.CalimWaWafid.Rafed0003477VolsBK27-ara2"
    ]
  },
  "0246QasimRassi.CuzzatBiLugha": {
    "external_id": "",
    "genre_tags": [
      "Zaydiyya@مجاميع أئمة أهل البيت"
    ],
    "relations": [
      {
        "dest": "0246QasimRassi.Majmuc",
        "main_rel_type": "PART",
        "sec_rel_type": "",
        "source": "0246QasimRassi.CuzzatBiLugha"
      }
    ],
    "title_ar": [
      "العظات باللغ"
    ],
    "title_lat": [
      "al-ʿUẓẓāt bi-al-luġa"
    ],
    "uri": "0246QasimRassi.CuzzatBiLugha",
    "versions": [
      "0246QasimRassi.CuzzatBiLugha.Zaydiyya0000075BK28-ara1",
      "0246QasimRassi.CuzzatBiLugha.Rafed0003477VolsBK28-ara2"
    ]
  },
  "0246QasimRassi.DalilKabir": {
    "external_id": "",
    "genre_tags": [
      "Zaydiyya@مجاميع أئمة أهل البيت"
    ],
    "relations": [
      {
        "dest": "0246QasimRassi.Majmuc",
        "main_rel_type": "PART",
        "sec_rel_type": "",
        "source": "0246QasimRassi.DalilKabir"
      }
    ],
    "title_ar": [
      "الدليل الكبير"
    ],
    "title_lat": [
      "al-Dalīl al-Kabīr"
    ],
    "uri": "0246QasimRassi.DalilKabir",
    "versions": [
      "0246QasimRassi.DalilKabir.Rafed0003477VolsBK1-ara2",
      "0246QasimRassi.DalilKabir.Zaydiyya0000075BK1-ara1"
    ]
  },
  "0246QasimRassi.DalilSaghir": {
    "external_id": "",
    "genre_tags": [
      "Zaydiyya@مجاميع أئمة أهل البيت"
    ],
    "relations": [
      {
        "dest": "0246QasimRassi.Majmuc",
        "main_rel_type": "PART",
        "sec_rel_type": "",
        "source": "0246QasimRassi.DalilSaghir"
      }
    ],
    "title_ar": [
      "الدليل الصغير"
    ],
    "title_lat": [
      "al-Dalīl al-Ṣaġīr"
    ],
    "uri": "0246QasimRassi.DalilSaghir",
    "versions": [
      "0246QasimRassi.DalilSaghir.Rafed0003477VolsBK2-ara2",
      "0246QasimRassi.DalilSaghir.Zaydiyya0000075BK2-ara1"
    ]
  },
  "0246QasimRassi.FusulFiTawhid": {
    "external_id": "",
    "genre_tags": [
      "Zaydiyya@مجاميع أئمة أهل البيت"
    ],
    "relations": [
      {
        "dest": "0246QasimRassi.Majmuc",
        "main_rel_type": "PART",
        "sec_rel_type": "",
        "source": "0246QasimRassi.FusulFiTawhid"
      }
    ],
    "title_ar": [
      "فصول في التوحيد"
    ],
    "title_lat": [
      "Fuṣūl fī al-tawḥīd"
    ],
    "uri": "0246QasimRassi.FusulFiTawhid",
    "versions": [
      "0246QasimRassi.FusulFiTawhid.Zaydiyya0000075BK11-ara1",
      "0246QasimRassi.FusulFiTawhid.Rafed0003477VolsBK13-ara2"
    ]
  },
  "0246QasimRassi.HijraLiZalimin": {
    "external_id": "",
    "genre_tags": [
      "Zaydiyya@مجاميع أئمة أهل البيت"
    ],
    "relations": [
      {
        "dest": "0246QasimRassi.Majmuc",
        "main_rel_type": "PART",
        "sec_rel_type": "",
        "source": "0246QasimRassi.HijraLiZalimin"
      }
    ],
    "title_ar": [
      "الهجر لالظالمين"
    ],
    "title_lat": [
      "al-Hiǧra li-al-Ẓālimīn"
    ],
    "uri": "0246QasimRassi.HijraLiZalimin",
    "versions": [
      "0246QasimRassi.HijraLiZalimin.Rafed0003477VolsBK24-ara2",
      "0246QasimRassi.HijraLiZalimin.Zaydiyya0000075BK22-ara1"
    ]
  },
  "0246QasimRassi.ImamMuftaridTaca": {
    "external_id": "",
    "genre_tags": [
      "Zaydiyya@مجاميع أئمة أهل البيت"
    ],
    "relations": [
      {
        "dest": "0246QasimRassi.Majmuc",
        "main_rel_type": "PART",
        "sec_rel_type": "",
        "source": "0246QasimRassi.ImamMuftaridTaca"
      }
    ],
    "title_ar": [
      "الامام المفترض الطاعة"
    ],
    "title_lat": [
      "al-Imām al-muftariḍ al-ṭāʿaŧ"
    ],
    "uri": "0246QasimRassi.ImamMuftaridTaca",
    "versions": [
      "0246QasimRassi.ImamMuftaridTaca.Rafed0003477VolsBK20-ara2",
      "0246QasimRassi.ImamMuftaridTaca.Zaydiyya0000075BK19-ara1"
    ]
  },
  "0246QasimRassi.ImamaQablCali": {
    "external_id": "",
    "genre_tags": [
      "Zaydiyya@مجاميع أئمة أهل البيت"
    ],
    "relations": [
      {
        "dest": "0246QasimRassi.Majmuc",
        "main_rel_type": "PART",
        "sec_rel_type": "",
        "source": "0246QasimRassi.ImamaQablCali"
      }
    ],
    "title_ar": [
      "الامامة قبل علي بن أبي طالب"
    ],
    "title_lat": [
      "al-Imāmaŧ qabl ʿAlī b. Abī Ṭālib"
    ],
    "uri": "0246QasimRassi.ImamaQablCali",
    "versions": [
      "0246QasimRassi.ImamaQablCali.Zaydiyya0000075BK20-ara1",
      "0246QasimRassi.ImamaQablCali.Rafed0003477VolsBK21-ara2"
    ]
  },
  "0246QasimRassi.ImamatCali": {
    "external_id": "",
    "genre_tags": [
      "Zaydiyya@مجاميع أئمة أهل البيت"
    ],
    "relations": [
      {
        "dest": "0246QasimRassi.Majmuc",
        "main_rel_type": "PART",
        "sec_rel_type": "",
        "source": "0246QasimRassi.ImamatCali"
      }
    ],
    "title_ar": [
      "امامة علي بن أبي طالب"
    ],
    "title_lat": [
      "Imāmaŧ ʿAlī b. Abī Ṭālib"
    ],
    "uri": "0246QasimRassi.ImamatCali",
    "versions": [
      "0246QasimRassi.ImamatCali.Zaydiyya0000075BK21-ara1",
      "0246QasimRassi.ImamatCali.Rafed0003477VolsBK22-ara2"
    ]
  },
  "0246QasimRassi.KamilMunir": {
    "external_id": "",
    "genre_tags": [
      "Zaydiyya@التوحيد وأصول الدين"
    ],
    "relations": [],
    "title_ar": [
      "الكامل المنير(الجزء الأول)",
      "الكامل المنير(المقدمة + الجزء الأول)",
      "الكامل المنير في إثبات ولاية أمير المؤمنين(ع)"
    ],
    "title_lat": [
      "Kamil Munir"
    ],
    "uri": "0246QasimRassi.KamilMunir",
    "versions": [
      "0246QasimRassi.KamilMunir.Zaydiyya0000222-ara1",
      "0246QasimRassi.KamilMunir.Zaydiyya0000003-ara1"
    ]
  },
  "0246QasimRassi.KitabFihiMasail": {
    "external_id": "",
    "genre_tags": [
      "Zaydiyya@للتنظيم"
    ],
    "relations": [],
    "title_ar": [
      "كتاب فيه مسائل عن القاسم بن إبراهيم(ع)"
    ],
    "title_lat": [
      "Kitab Fihi Masail"
    ],
    "uri": "0246QasimRassi.KitabFihiMasail",
    "versions": [
      "0246QasimRassi.KitabFihiMasail.Zaydiyya0000408-ara1"
    ]
  },
  "0246QasimRassi.MadihQuranKabir": {
    "external_id": "",
    "genre_tags": [
      "Zaydiyya@مجاميع أئمة أهل البيت"
    ],
    "relations": [
      {
        "dest": "0246QasimRassi.Majmuc",
        "main_rel_type": "PART",
        "sec_rel_type": "",
        "source": "0246QasimRassi.MadihQuranKabir"
      }
    ],
    "title_ar": [
      "مديح القرآن الكبير"
    ],
    "title_lat": [
      "Madīḥ al-Qurʾān al-kabīr"
    ],
    "uri": "0246QasimRassi.MadihQuranKabir",
    "versions": [
      "0246QasimRassi.MadihQuranKabir.Zaydiyya0000075BK15-ara1",
      "0246QasimRassi.MadihQuranKabir.Rafed0003477VolsBK15-ara2"
    ]
  },
  "0246QasimRassi.MadihQuranSaghir": {
    "external_id": "",
    "genre_tags": [
      "Zaydiyya@مجاميع أئمة أهل البيت"
    ],
    "relations": [
      {
        "dest": "0246QasimRassi.Majmuc",
        "main_rel_type": "PART",
        "sec_rel_type": "",
        "source": "0246QasimRassi.MadihQuranSaghir"
      }
    ],
    "title_ar": [
      "مديح القرآن الصغير"
    ],
    "title_lat": [
      "Madīḥ al-Qurʾān al-ṣaġīr"
    ],
    "uri": "0246QasimRassi.MadihQuranSaghir",
    "versions": [
      "0246QasimRassi.MadihQuranSaghir.Zaydiyya0000075BK16-ara1",
      "0246QasimRassi.MadihQuranSaghir.Rafed0003477VolsBK16-ara2"
    ]
  },
  "0246QasimRassi.MafahimIslamiyya": {
    "external_id": "",
    "genre_tags": [
      "Zaydiyya@مجاميع أئمة أهل البيت"
    ],
    "relations": [
      {
        "dest": "0246QasimRassi.Majmuc",
        "main_rel_type": "PART",
        "sec_rel_type": "",
        "source": "0246QasimRassi.MafahimIslamiyya"
      }
    ],
    "title_ar": [
      "المفاهيم الاسلامية"
    ],
    "title_lat": [
      "al-Mafāhīm al-islāmiyyaŧ"
    ],
    "uri": "0246QasimRassi.MafahimIslamiyya",
    "versions": [
      "0246QasimRassi.MafahimIslamiyya.Rafed0003477VolsBK29-ara2",
      "0246QasimRassi.MafahimIslamiyya.Zaydiyya0000075BK26-ara1"
    ]
  },
  "0246QasimRassi.Majmuc": {
    "relations": [
      {
        "dest": "0246QasimRassi.Majmuc",
        "main_rel_type": "PART",
        "sec_rel_type": "",
        "source": "0246QasimRassi.CadlWaTawhid"
      },
      {
        "dest": "0246QasimRassi.Majmuc",
        "main_rel_type": "PART",
        "sec_rel_type": "",
        "source": "0246QasimRassi.CalimWaWafid"
      },
      {
        "dest": "0246QasimRassi.Majmuc",
        "main_rel_type": "PART",
        "sec_rel_type": "",
        "source": "0246QasimRassi.CuzzatBiLugha"
      },
      {
        "dest": "0246QasimRassi.Majmuc",
        "main_rel_type": "PART",
        "sec_rel_type": "",
        "source": "0246QasimRassi.DalilKabir"
      },
      {
        "dest": "0246QasimRassi.Majmuc",
        "main_rel_type": "PART",
        "sec_rel_type": "",
        "source": "0246QasimRassi.DalilSaghir"
      },
      {
        "dest": "0246QasimRassi.Majmuc",
        "main_rel_type": "PART",
        "sec_rel_type": "",
        "source": "0246QasimRassi.FusulFiTawhid"
      },
      {
        "dest": "0246QasimRassi.Majmuc",
        "main_rel_type": "PART",
        "sec_rel_type": "",
        "source": "0246QasimRassi.HijraLiZalimin"
      },
      {
        "dest": "0246QasimRassi.Majmuc",
        "main_rel_type": "PART",
        "sec_rel_type": "",
        "source": "0246QasimRassi.ImamMuftaridTaca"
      },
      {
        "dest": "0246QasimRassi.Majmuc",
        "main_rel_type": "PART",
        "sec_rel_type": "",
        "source": "0246QasimRassi.ImamaQablCali"
      },
      {
        "dest": "0246QasimRassi.Majmuc",
        "main_rel_type": "PART",
        "sec_rel_type": "",
        "source": "0246QasimRassi.ImamatCali"
      },
      {
        "dest": "0246QasimRassi.Majmuc",
        "main_rel_type": "PART",
        "sec_rel_type": "",
        "source": "0246QasimRassi.MadihQuranKabir"
      },
      {
        "dest": "0246QasimRassi.Majmuc",
        "main_rel_type": "PART",
        "sec_rel_type": "",
        "source": "0246QasimRassi.MadihQuranSaghir"
      },
      {
        "dest": "0246QasimRassi.Majmuc",
        "main_rel_type": "PART",
        "sec_rel_type": "",
        "source": "0246QasimRassi.MafahimIslamiyya"
      },
      {
        "dest": "0246QasimRassi.Majmuc",
        "main_rel_type": "PART",
        "sec_rel_type": "",
        "source": "0246QasimRassi.Maknun"
      },
      {
        "dest": "0246QasimRassi.Majmuc",
        "main_rel_type": "PART",
        "sec_rel_type": "",
        "source": "0246QasimRassi.Masail"
      },
      {
        "dest": "0246QasimRassi.Majmuc",
        "main_rel_type": "PART",
        "sec_rel_type": "",
        "source": "0246QasimRassi.MasalaLiRajulayn"
      },
      {
        "dest": "0246QasimRassi.Majmuc",
        "main_rel_type": "PART",
        "sec_rel_type": "",
        "source": "0246QasimRassi.MunazaraMacaMulhid"
      },
      {
        "dest": "0246QasimRassi.Majmuc",
        "main_rel_type": "PART",
        "sec_rel_type": "",
        "source": "0246QasimRassi.Mustarshid"
      },
      {
        "dest": "0246QasimRassi.Majmuc",
        "main_rel_type": "PART",
        "sec_rel_type": "",
        "source": "0246QasimRassi.NasikhWaMansukh"
      },
      {
        "dest": "0246QasimRassi.Majmuc",
        "main_rel_type": "PART",
        "sec_rel_type": "",
        "source": "0246QasimRassi.Qatl"
      },
      {
        "dest": "0246QasimRassi.Majmuc",
        "main_rel_type": "PART",
        "sec_rel_type": "",
        "source": "0246QasimRassi.RaddCalaMujabbira"
      },
      {
        "dest": "0246QasimRassi.Majmuc",
        "main_rel_type": "PART",
        "sec_rel_type": "",
        "source": "0246QasimRassi.RaddCalaNasara"
      },
      {
        "dest": "0246QasimRassi.Majmuc",
        "main_rel_type": "PART",
        "sec_rel_type": "",
        "source": "0246QasimRassi.RaddCalaRafida"
      },
      {
        "dest": "0246QasimRassi.Majmuc",
        "main_rel_type": "PART",
        "sec_rel_type": "",
        "source": "0246QasimRassi.RaddCalaRawafid"
      },
      {
        "dest": "0246QasimRassi.Majmuc",
        "main_rel_type": "PART",
        "sec_rel_type": "",
        "source": "0246QasimRassi.RaddCalaZindiq"
      },
      {
        "dest": "0246QasimRassi.Majmuc",
        "main_rel_type": "PART",
        "sec_rel_type": "",
        "source": "0246QasimRassi.SalatYawmWaLayla"
      },
      {
        "dest": "0246QasimRassi.Majmuc",
        "main_rel_type": "PART",
        "sec_rel_type": "",
        "source": "0246QasimRassi.SiyasatNafs"
      },
      {
        "dest": "0246QasimRassi.Majmuc",
        "main_rel_type": "PART",
        "sec_rel_type": "",
        "source": "0246QasimRassi.TafsirCarshWaKursi"
      },
      {
        "dest": "0246QasimRassi.Majmuc",
        "main_rel_type": "PART",
        "sec_rel_type": "",
        "source": "0246QasimRassi.TafsirQuran"
      },
      {
        "dest": "0246QasimRassi.Majmuc",
        "main_rel_type": "PART",
        "sec_rel_type": "",
        "source": "0246QasimRassi.Tahara"
      },
      {
        "dest": "0246QasimRassi.Majmuc",
        "main_rel_type": "PART",
        "sec_rel_type": "",
        "source": "0246QasimRassi.TathbitImama"
      },
      {
        "dest": "0246QasimRassi.Majmuc",
        "main_rel_type": "PART",
        "sec_rel_type": "",
        "source": "0246QasimRassi.UsulCadlWaTawhid"
      }
    ]
  },
  "0246QasimRassi.Maknun": {
    "external_id": "",
    "genre_tags": [
      "Zaydiyya@مجاميع أئمة أهل البيت"
    ],
    "relations": [
      {
        "dest": "0246QasimRassi.Majmuc",
        "main_rel_type": "PART",
        "sec_rel_type": "",
        "source": "0246QasimRassi.Maknun"
      }
    ],
    "title_ar": [
      "المكنون"
    ],
    "title_lat": [
      "al-Maknūn"
    ],
    "uri": "0246QasimRassi.Maknun",
    "versions": [
      "0246QasimRassi.Maknun.Zaydiyya0000075BK24-ara1",
      "0246QasimRassi.Maknun.Rafed0003477VolsBK25-ara2"
    ]
  },
  "0246QasimRassi.Masail": {
    "external_id": "",
    "genre_tags": [
      "Zaydiyya@مجاميع أئمة أهل البيت"
    ],
    "relations": [
      {
        "dest": "0246QasimRassi.Majmuc",
        "main_rel_type": "PART",
        "sec_rel_type": "",
        "source": "0246QasimRassi.Masail"
      }
    ],
    "title_ar": [
      "مسائل القاسم الرسي"
    ],
    "title_lat": [
      "Masāʾil al-Qāsim al-Rassī"
    ],
    "uri": "0246QasimRassi.Masail",
    "versions": [
      "0246QasimRassi.Masail.Rafed0003477VolsBK32-ara2",
      "0246QasimRassi.Masail.Zaydiyya0000075BK32-ara1"
    ]
  },
  "0246QasimRassi.MasalaLiRajulayn": {
    "external_id": "",
    "genre_tags": [
      "Zaydiyya@مجاميع أئمة أهل البيت"
    ],
    "relations": [
      {
        "dest": "0246QasimRassi.Majmuc",
        "main_rel_type": "PART",
        "sec_rel_type": "",
        "source": "0246QasimRassi.MasalaLiRajulayn"
      }
    ],
    "title_ar": [
      "جواب مسألة لرجلين من أهل طبرستان"
    ],
    "title_lat": [
      "Jawāb masʾalaŧ li-raǧulayn min ahl Ṭabaristān"
    ],
    "uri": "0246QasimRassi.MasalaLiRajulayn",
    "versions": [
      "0246QasimRassi.MasalaLiRajulayn.Rafed0003477VolsBK12-ara2",
      "0246QasimRassi.MasalaLiRajulayn.Zaydiyya0000075BK6-ara1"
    ]
  },
  "0246QasimRassi.MunazaraMacaMulhid": {
    "external_id": "",
    "genre_tags": [
      "Zaydiyya@مجاميع أئمة أهل البيت"
    ],
    "relations": [
      {
        "dest": "0246QasimRassi.Majmuc",
        "main_rel_type": "PART",
        "sec_rel_type": "",
        "source": "0246QasimRassi.MunazaraMacaMulhid"
      }
    ],
    "title_ar": [
      "مناظر مع ملحد"
    ],
    "title_lat": [
      "Munāẓara Maʿa Mulḥid"
    ],
    "uri": "0246QasimRassi.MunazaraMacaMulhid",
    "versions": [
      "0246QasimRassi.MunazaraMacaMulhid.Rafed0003477VolsBK3-ara2",
      "0246QasimRassi.MunazaraMacaMulhid.Zaydiyya0000075BK3-ara1"
    ]
  },
  "0246QasimRassi.Mustarshid": {
    "external_id": "",
    "genre_tags": [
      "Zaydiyya@مجاميع أئمة أهل البيت"
    ],
    "relations": [
      {
        "dest": "0246QasimRassi.Majmuc",
        "main_rel_type": "PART",
        "sec_rel_type": "",
        "source": "0246QasimRassi.Mustarshid"
      }
    ],
    "title_ar": [
      "المسترشد"
    ],
    "title_lat": [
      "al-Mustaršid"
    ],
    "uri": "0246QasimRassi.Mustarshid",
    "versions": [
      "0246QasimRassi.Mustarshid.Zaydiyya0000075BK8-ara1",
      "0246QasimRassi.Mustarshid.Rafed0003477VolsBK6-ara2"
    ]
  },
  "0246QasimRassi.NasikhWaMansukh": {
    "external_id": "",
    "genre_tags": [
      "Zaydiyya@مجاميع أئمة أهل البيت"
    ],
    "relations": [
      {
        "dest": "0246QasimRassi.Majmuc",
        "main_rel_type": "PART",
        "sec_rel_type": "",
        "source": "0246QasimRassi.NasikhWaMansukh"
      }
    ],
    "title_ar": [
      "الناسخ والمنسوخ"
    ],
    "title_lat": [
      "al-Nāsiḫ wa-al-mansūḫ"
    ],
    "uri": "0246QasimRassi.NasikhWaMansukh",
    "versions": [
      "0246QasimRassi.NasikhWaMansukh.Zaydiyya0000075BK17-ara1",
      "0246QasimRassi.NasikhWaMansukh.Rafed0003477VolsBK17-ara2"
    ]
  },
  "0246QasimRassi.Qatl": {
    "external_id": "",
    "genre_tags": [
      "Zaydiyya@مجاميع أئمة أهل البيت"
    ],
    "relations": [
      {
        "dest": "0246QasimRassi.Majmuc",
        "main_rel_type": "PART",
        "sec_rel_type": "",
        "source": "0246QasimRassi.Qatl"
      }
    ],
    "title_ar": [
      "القتل والقتال"
    ],
    "title_lat": [
      "al-Qatl wa-al-qitāl"
    ],
    "uri": "0246QasimRassi.Qatl",
    "versions": [
      "0246QasimRassi.Qatl.Zaydiyya0000075BK23-ara1",
      "0246QasimRassi.Qatl.Rafed0003477VolsBK23-ara2"
    ]
  },
  "0246QasimRassi.RaddCalaMujabbira": {
    "external_id": "",
    "genre_tags": [
      "Zaydiyya@مجاميع أئمة أهل البيت"
    ],
    "relations": [
      {
        "dest": "0246QasimRassi.Majmuc",
        "main_rel_type": "PART",
        "sec_rel_type": "",
        "source": "0246QasimRassi.RaddCalaMujabbira"
      }
    ],
    "title_ar": [
      "الرد على المجبرة"
    ],
    "title_lat": [
      "al-Radd ʿalá al-Muǧabbiraŧ"
    ],
    "uri": "0246QasimRassi.RaddCalaMujabbira",
    "versions": [
      "0246QasimRassi.RaddCalaMujabbira.Zaydiyya0000075BK12-ara1",
      "0246QasimRassi.RaddCalaMujabbira.Rafed0003477VolsBK7-ara2"
    ]
  },
  "0246QasimRassi.RaddCalaNasara": {
    "external_id": "",
    "genre_tags": [
      "Zaydiyya@مجاميع أئمة أهل البيت"
    ],
    "relations": [
      {
        "dest": "0246QasimRassi.Majmuc",
        "main_rel_type": "PART",
        "sec_rel_type": "",
        "source": "0246QasimRassi.RaddCalaNasara"
      }
    ],
    "title_ar": [
      "الرد على النصارى"
    ],
    "title_lat": [
      "al-Radd ʿalá al-naṣārá"
    ],
    "uri": "0246QasimRassi.RaddCalaNasara",
    "versions": [
      "0246QasimRassi.RaddCalaNasara.Rafed0003477VolsBK5-ara2",
      "0246QasimRassi.RaddCalaNasara.Zaydiyya0000075BK5-ara1"
    ]
  },
  "0246QasimRassi.RaddCalaRafida": {
    "external_id": "",
    "genre_tags": [
      "Zaydiyya@مجاميع أئمة أهل البيت"
    ],
    "relations": [
      {
        "dest": "0246QasimRassi.Majmuc",
        "main_rel_type": "PART",
        "sec_rel_type": "",
        "source": "0246QasimRassi.RaddCalaRafida"
      }
    ],
    "title_ar": [
      "الرد على الرافضة"
    ],
    "title_lat": [
      "al-Radd ʿalá al-Rāfiḍaŧ"
    ],
    "uri": "0246QasimRassi.RaddCalaRafida",
    "versions": [
      "0246QasimRassi.RaddCalaRafida.Rafed0003477VolsBK8-ara2",
      "0246QasimRassi.RaddCalaRafida.Zaydiyya0000075BK13-ara1"
    ]
  },
  "0246QasimRassi.RaddCalaRawafid": {
    "external_id": "",
    "genre_tags": [
      "Zaydiyya@مجاميع أئمة أهل البيت"
    ],
    "relations": [
      {
        "dest": "0246QasimRassi.Majmuc",
        "main_rel_type": "PART",
        "sec_rel_type": "",
        "source": "0246QasimRassi.RaddCalaRawafid"
      }
    ],
    "title_ar": [
      "الرد على الروافض من أهل الغلو"
    ],
    "title_lat": [
      "al-Radd ʿalá al-Rawāfiḍ min ahl al-ġuluww"
    ],
    "uri": "0246QasimRassi.RaddCalaRawafid",
    "versions": [
      "0246QasimRassi.RaddCalaRawafid.Zaydiyya0000075BK14-ara1",
      "0246QasimRassi.RaddCalaRawafid.Rafed0003477VolsBK9-ara2"
    ]
  },
  "0246QasimRassi.RaddCalaZindiq": {
    "external_id": "",
    "genre_tags": [
      "Zaydiyya@مجاميع أئمة أهل البيت"
    ],
    "relations": [
      {
        "dest": "0246QasimRassi.Majmuc",
        "main_rel_type": "PART",
        "sec_rel_type": "",
        "source": "0246QasimRassi.RaddCalaZindiq"
      }
    ],
    "title_ar": [
      "الرد على الزنديق ابن المقفى"
    ],
    "title_lat": [
      "al-Radd ʿalá al-zindīq Ibn al-Muqaffá"
    ],
    "uri": "0246QasimRassi.RaddCalaZindiq",
    "versions": [
      "0246QasimRassi.RaddCalaZindiq.Zaydiyya0000075BK4-ara1",
      "0246QasimRassi.RaddCalaZindiq.Rafed0003477VolsBK4-ara2"
    ]
  },
  "0246QasimRassi.SalatYawmWaLayla": {
    "external_id": "",
    "genre_tags": [
      "Zaydiyya@مجاميع أئمة أهل البيت"
    ],
    "relations": [
      {
        "dest": "0246QasimRassi.Majmuc",
        "main_rel_type": "PART",
        "sec_rel_type": "",
        "source": "0246QasimRassi.SalatYawmWaLayla"
      }
    ],
    "title_ar": [
      "صلاة اليوم والليلة"
    ],
    "title_lat": [
      "Ṣalāŧ al-yawm wa-al-laylaŧ"
    ],
    "uri": "0246QasimRassi.SalatYawmWaLayla",
    "versions": [
      "0246QasimRassi.SalatYawmWaLayla.Zaydiyya0000075BK31-ara1",
      "0246QasimRassi.SalatYawmWaLayla.Rafed0003477VolsBK31-ara2"
    ]
  },
  "0246QasimRassi.SiyasatNafs": {
    "external_id": "",
    "genre_tags": [
      "Zaydiyya@مجاميع أئمة أهل البيت"
    ],
    "relations": [
      {
        "dest": "0246QasimRassi.Majmuc",
        "main_rel_type": "PART",
        "sec_rel_type": "",
        "source": "0246QasimRassi.SiyasatNafs"
      }
    ],
    "title_ar": [
      "سياست النفس"
    ],
    "title_lat": [
      "Siyāsat al-nafs"
    ],
    "uri": "0246QasimRassi.SiyasatNafs",
    "versions": [
      "0246QasimRassi.SiyasatNafs.Rafed0003477VolsBK26-ara2",
      "0246QasimRassi.SiyasatNafs.Zaydiyya0000075BK25-ara1"
    ]
  },
  "0246QasimRassi.TafsirCarshWaKursi": {
    "external_id": "",
    "genre_tags": [
      "Zaydiyya@مجاميع أئمة أهل البيت"
    ],
    "relations": [
      {
        "dest": "0246QasimRassi.Majmuc",
        "main_rel_type": "PART",
        "sec_rel_type": "",
        "source": "0246QasimRassi.TafsirCarshWaKursi"
      }
    ],
    "title_ar": [
      "تفسير العرش والكرسي"
    ],
    "title_lat": [
      "Tafsīr al-ʿarš wa-al-kursī"
    ],
    "uri": "0246QasimRassi.TafsirCarshWaKursi",
    "versions": [
      "0246QasimRassi.TafsirCarshWaKursi.Rafed0003477VolsBK14-ara2",
      "0246QasimRassi.TafsirCarshWaKursi.Zaydiyya0000075BK9-ara1"
    ]
  },
  "0246QasimRassi.TafsirQuran": {
    "external_id": "",
    "genre_tags": [
      "Zaydiyya@مجاميع أئمة أهل البيت"
    ],
    "relations": [
      {
        "dest": "0246QasimRassi.Majmuc",
        "main_rel_type": "PART",
        "sec_rel_type": "",
        "source": "0246QasimRassi.TafsirQuran"
      }
    ],
    "title_ar": [
      "تفسير القرآن"
    ],
    "title_lat": [
      "Tafsīr al-Qurʾān"
    ],
    "uri": "0246QasimRassi.TafsirQuran",
    "versions": [
      "0246QasimRassi.TafsirQuran.Rafed0003477VolsBK18-ara2",
      "0246QasimRassi.TafsirQuran.Zaydiyya0000075BK29-ara1"
    ]
  },
  "0246QasimRassi.Tahara": {
    "external_id": "",
    "genre_tags": [
      "Zaydiyya@مجاميع أئمة أهل البيت"
    ],
    "relations": [
      {
        "dest": "0246QasimRassi.Majmuc",
        "main_rel_type": "PART",
        "sec_rel_type": "",
        "source": "0246QasimRassi.Tahara"
      }
    ],
    "title_ar": [
      "الطهار"
    ],
    "title_lat": [
      "al-Ṭahāra"
    ],
    "uri": "0246QasimRassi.Tahara",
    "versions": [
      "0246QasimRassi.Tahara.Rafed0003477VolsBK30-ara2",
      "0246QasimRassi.Tahara.Zaydiyya0000075BK30-ara1"
    ]
  },
  "0246QasimRassi.TathbitImama": {
    "external_id": "",
    "genre_tags": [
      "_SHICI",
      "GAL@nodata",
      "_CAQAID",
      "CENT0300",
      "_ZAYDIYYA",
      "Shia@من مصادر العقائد عند الشيعة الزيدية",
      "Zaydiyya@مجاميع أئمة أهل البيت"
    ],
    "relations": [
      {
        "dest": "0246QasimRassi.Majmuc",
        "main_rel_type": "PART",
        "sec_rel_type": "",
        "source": "0246QasimRassi.TathbitImama"
      }
    ],
    "title_ar": [
      "تثبيت الامامة"
    ],
    "title_lat": [
      "Taṯbīt al-Imāmaŧ"
    ],
    "uri": "0246QasimRassi.TathbitImama",
    "versions": [
      "0246QasimRassi.TathbitImama.Shia004484-ara1",
      "0246QasimRassi.TathbitImama.Zaydiyya0000075BK18-ara1",
      "0246QasimRassi.TathbitImama.Rafed0003477VolsBK19-ara2"
    ]
  },
  "0246QasimRassi.UsulCadlWaTawhid": {
    "external_id": "",
    "genre_tags": [
      "Zaydiyya@مجاميع أئمة أهل البيت"
    ],
    "relations": [
      {
        "dest": "0246QasimRassi.Majmuc",
        "main_rel_type": "PART",
        "sec_rel_type": "",
        "source": "0246QasimRassi.UsulCadlWaTawhid"
      }
    ],
    "title_ar": [
      "أصول العدل والتوحيد"
    ],
    "title_lat": [
      "Uṣūl al-ʿadl wa-al-tawḥīd"
    ],
    "uri": "0246QasimRassi.UsulCadlWaTawhid",
    "versions": [
      "0246QasimRassi.UsulCadlWaTawhid.Zaydiyya0000075BK10-ara1",
      "0246QasimRassi.UsulCadlWaTawhid.Rafed0003477VolsBK11-ara2"
    ]
  },
  "0247AhmadIbnCisa.Amali": {
    "external_id": "",
    "genre_tags": [
      "Zaydiyya@الحديث"
    ],
    "relations": [],
    "title_ar": [
      "أمالي الإمام أحمد بن عيسى"
    ],
    "title_lat": [
      "Amali"
    ],
    "uri": "0247AhmadIbnCisa.Amali",
    "versions": [
      "0247AhmadIbnCisa.Amali.Zaydiyya0000049-ara1"
    ]
  },
  "0249AbuBishrTamimi.Tarikh": {
    "external_id": "",
    "genre_tags": [
      "ShamAY@مخطوطات حديثية"
    ],
    "relations": [],
    "title_ar": [
      "تاريخ أبي بشر هارون بن حاتم التميمي - مخطوط ",
      "تاريخ أبي بشر هارون بن حاتم التميمي - مخطوط"
    ],
    "title_lat": [
      "Tarikh"
    ],
    "uri": "0249AbuBishrTamimi.Tarikh",
    "versions": [
      "0249AbuBishrTamimi.Tarikh.ShamAY0032915-ara1"
    ]
  },
  "0249Azraqi.AkhbarMakka": {
    "external_id": "",
    "genre_tags": [
      "_JUGHRAFIYA",
      "ShamAY@التاريخ",
      "JK@السير والتاريخ",
      "JK@تواريخ البلدان",
      "JK@كتب البلدان",
      "JK@كتب الحديث النبوي الشريف وتراجم الرواة",
      "Shamela@متون الحديث"
    ],
    "relations": [
      {
        "dest": "0227AbuMuhammadAzraqi.Makka",
        "main_rel_type": "CONT",
        "sec_rel_type": "",
        "source": "0249Azraqi.AkhbarMakka"
      }
    ],
    "title_ar": [
      "أخبار مكة المشرفة",
      ""
    ],
    "title_lat": [
      "Aḫbār Makkaŧ al-Mušarrafaaŧ",
      ""
    ],
    "uri": "0249Azraqi.AkhbarMakka",
    "versions": [
      "0249Azraqi.AkhbarMakka.ShamAY0033816-ara1",
      "0249Azraqi.AkhbarMakka.JK003504-ara1",
      "0249Azraqi.AkhbarMakka.Shamela0009621-ara1"
    ]
  },
  "0249CabdIbnHamid.MinCawaliMusnad": {
    "external_id": "",
    "genre_tags": [
      "_HADITH",
      "CENT0300",
      "_MAKHTUTAT",
      "GAL@nodata",
      "Shamela@مخطوطات حديثية"
    ],
    "relations": [],
    "title_ar": [
      "من عوالي مسند عبد بن حميد - مخطوط"
    ],
    "title_lat": [
      "Min Cawali Musnad"
    ],
    "uri": "0249CabdIbnHamid.MinCawaliMusnad",
    "versions": [
      "0249CabdIbnHamid.MinCawaliMusnad.Shamela0021676-ara1"
    ]
  },
  "0249CabdIbnHamid.MuntakhabMinMusnad": {
    "external_id": "",
    "genre_tags": [
      "_MASANID",
      "_MACAJIM",
      "_SUNNI",
      "GAL@nodata",
      "_TARAJIM",
      "_HADITH",
      "CENT0300",
      "JK@المسانيد والمعاجم",
      "JK@كتب الحديث النبوي الشريف وتراجم الرواة",
      "Shamela@متون الحديث",
      "Shia@مصادر الحديث السنية ـ القسم العام",
      "ShamAY@متون الحديث"
    ],
    "relations": [],
    "title_ar": [
      "المنتخب من مسند عبد بن حميد",
      "مسند عبد بن حميد",
      "منتخب مسند عبد بن حميد",
      "المنتخب من مسند عبد بن حميد ",
      "المنتخب من مسند عبد بن حميد - مكتبة ابن عباس"
    ],
    "title_lat": [
      "Muntakhab Min Musnad"
    ],
    "uri": "0249CabdIbnHamid.MuntakhabMinMusnad",
    "versions": [
      "0249CabdIbnHamid.MuntakhabMinMusnad.JK000486-ara1",
      "0249CabdIbnHamid.MuntakhabMinMusnad.Shamela0010631-ara2",
      "0249CabdIbnHamid.MuntakhabMinMusnad.Shia001920-ara1",
      "0249CabdIbnHamid.MuntakhabMinMusnad.Shamela0013170-ara1",
      "0249CabdIbnHamid.MuntakhabMinMusnad.ShamAY0033973-ara1"
    ]
  },
  "0249IbnBarqiMuhammad.TamyizThiqat": {
    "external_id": "",
    "genre_tags": [
      "ShamAY@التراجم والطبقات"
    ],
    "relations": [],
    "title_ar": [
      "تمييز ثقات المحدثين وضعفائهم وأسمائهم وكناهم لابن البرقي",
      "تمييز ثقات المحدثين وضعفائهم وأسمائهم وكناهم ",
      "تمييز ثقات المحدثين وضعفائهم وأسمائهم وكناهم"
    ],
    "title_lat": [
      "Tamyiz Thiqat"
    ],
    "uri": "0249IbnBarqiMuhammad.TamyizThiqat",
    "versions": [
      "0249IbnBarqiMuhammad.TamyizThiqat.ShamAY0034628-ara1"
    ]
  },
  "0250AflahIbnCabdWahhab.Jawabat": {
    "external_id": "",
    "genre_tags": [
      "ShamIbadiyya@فقه"
    ],
    "relations": [],
    "title_ar": [
      "من جوابات الإمام أفلح بن عبد الوهاب تحقيق عمر فخار - ب تخرج"
    ],
    "title_lat": [
      "Jawabat"
    ],
    "uri": "0250AflahIbnCabdWahhab.Jawabat",
    "versions": [
      "0250AflahIbnCabdWahhab.Jawabat.ShamIbadiyya0000784-ara1"
    ]
  },
  "0250CabdMasihNacimi.SufistiqaLiAristutalis": {
    "external_id": "",
    "genre_tags": [],
    "relations": [],
    "title_ar": [
      "سوفسطيقا لأرسطوطاليس",
      ""
    ],
    "title_lat": [
      "Sūfisṭīqā li-Arisṭūṭālīs",
      ""
    ],
    "uri": "0250CabdMasihNacimi.SufistiqaLiAristutalis",
    "versions": [
      "0250CabdMasihNacimi.SufistiqaLiAristutalis.GRAR000028-ara1"
    ]
  },
  "0250IbnCatiyyaShami.Ahadith": {
    "external_id": "",
    "genre_tags": [
      "ShamAY@مخطوطات حديثية"
    ],
    "relations": [],
    "title_ar": [
      "أحاديث مستخرجة من كتاب الخلافة لمحمد بن عطية الشامي - مخطوط ",
      "أحاديث مستخرجة من كتاب الخلافة لمحمد بن عطية الشامي - مخطوط",
      "أحاديث مستخرجة من كتاب الخلافة لمحمد بن عطية الشامي- مخطوط"
    ],
    "title_lat": [
      "Ahadith"
    ],
    "uri": "0250IbnCatiyyaShami.Ahadith",
    "versions": [
      "0250IbnCatiyyaShami.Ahadith.ShamAY0032745-ara1"
    ]
  },
  "0250ThabitIbnAbiThabit.Farq": {
    "external_id": "",
    "genre_tags": [
      "_MACAJIM",
      "_GHARIB",
      "_MUSTALAHAT",
      "GAL@nodata",
      "_MASAIL",
      "CENT0300",
      "JK@كتب المعاجم والغريب والمصطلحات",
      "JK@مسائل في الغريب والمعاني",
      "Shamela@الغريب والمعاجم ولغة الفقه"
    ],
    "relations": [],
    "title_ar": [
      "الفرق"
    ],
    "title_lat": [
      "Farq"
    ],
    "uri": "0250ThabitIbnAbiThabit.Farq",
    "versions": [
      "0250ThabitIbnAbiThabit.Farq.JK006963-ara1",
      "0250ThabitIbnAbiThabit.Farq.Shamela0007055-ara1"
    ]
  }
}